Workbook
Name Faktisk: (TidsrumIFaktisk*([1]Projektplanlægger!$E1>0))*TidsrumIPlan
Name FaktiskUdOver: TidsrumIFaktisk*([1]Projektplanlægger!$E1>0)
Name Plan: TidsrumIPlan*([1]Projektplanlægger!$C1>0)
Name ProcentdelFuldført: ProcentdelFuldførtUdOver*TidsrumIPlan
Name TidsrumIFaktisk: [1]Projektplanlægger!A$4=MEDIAN([1]Projektplanlægger!A$4,[1]Projektplanlægger!$E1,[1]Projektplanlægger!$E1+[1]Projektplanlægger!$F1-1)
Name TidsrumIPlan: [1]Projektplanlægger!A$4=MEDIAN([1]Projektplanlægger!A$4,[1]Projektplanlægger!$C1,[1]Projektplanlægger!$C1+[1]Projektplanlægger!$D1-1)
Name valgt_tidsrum: [1]Projektplanlægger!$H$2

Sheet Beskrivelser
A3: 1) Hvordan planlægger vi projektet? (projektplan & tidslinje samt SWOT & risikovurdering)
A5: 2) Hvem er projektets interessenter, og hvordan kommunikerer vi med dem? (interessentanalyse & kommunikationsplan)
A7: 3) Hvordan skal organisationen se ud? Hvor mange medarbejdere skal der være? Hvilke arbejdsopgaver er der i organisationen? (organisationsdiagram og arbejdsbeskrivelser for afdelingerne)
A9: 4) Hvilket færdigvareprodukt skal vi sælge? (arbejdstegninger og BOM/stykliste)
A11: 5) Hvad vil vi selv fremstille, og hvad vil vi købe af leverandører? (MAKE-BUY beslutninger, BOM)
A13: 6) Hvilke fremstillingsmetoder skal vi bruge til de parter, vi vil fremstille? (operationsdiagram, illustrativ BOM)
A15: 7) Hvilke maskiner skal vi bruge til hvilke fremstillingsmetoder? (maskinliste og fremstillingsvalg)
A17: 8) Hvordan skal maskinerne placeres i faciliteterne? Hvordan ser faciliteterne ud? Hvor er lokationen? (faciliteter og produktionslayout)
A19: 9) Hvor lang tid tager det i alt at fremstille en stol? (procesdiagram). Hvordan viser vi operatørerne, hvordan de forskellige parter skal fremstilles? (operationskort)
A21: 10) Hvordan skal produktionen planlægges? Hvordan skal vedligehold af maskinerne planlægges? (Gantt-kort og vedligeholdelsesplan). Hvordan ser OEE ud? (OEE-udregninger)
A23: 11) Hvilke materialer skal vi bruge til at fremstille stolen? Og hvor mange materialer skal vi bruge? (lagerstyring)
A25: 12) Hvordan styrer vi virksomhedens materialeflow? (MRP - manufacturing ressource planning)
... A31: 15) Hvordan er investreringsrentabiliteten for projektet? (investeringsrentabilitet)

Sheet 1 Projektplan & risikovurdering
B2: SWOT
B3: Strengths | C3: Weaknesses | D3: Opportunities | E3: Threats
B4: Dansk design og produktion giver høj troværdighed og gør produktet attraktivt for kunder, der prioriterer kvalitet og lokal produktion. Lettere kommunikation og hurtigere beslutningsprocesser, fordi udvikling og produktion foregår samme sted. Nemmere at automatisere produktionen, da man har fuld kontrol over faciliteter, maskiner og arbejdsgange. Tættere på produktudviklingen, hvilket betyder hurtigere prototyper, færre fejl og bedre kvalitetssikring. | C4: Højere omkostninger til arbejdskraft i Danmark sammenlignet med mange andre produktionslande. Dyre lager- og produktionsfaciliteter, inkl. drift, energi og vedligehold. Dansk lovgivning og fagforeninger kan give ekstra krav, der påvirker fleksibiliteten og omkostningsniveauet. Risiko for forsyningskædeproblemer. Sårbarhed ved sygdom eller fravær, da mindre teams hurtigere mærker manglende bemanding. Logistiske udfordringer, fx hvis der skal leveres store mængder hurtigt. | D4: Kortere afstand til kunder i EU og nemmere eksport, da produktionen ligger centralt i Europa. Mulighed for at markedsføre høj kvalitet og EU-standarder, hvilket kan give en premium-positionering. Mulighed for at tiltrække dygtig europæisk arbejdskraft, hvis virksomheden vokser. Større fleksibilitet i produktændringer, fordi produktionen er tæt på udvikling og salg. | E4: Billigere udenlandske konkurrenter, som kan tilbyde lignende stole til lavere priser. Stigende materialepriser, som kan presse produktionen økonomisk. Produktionsstop ved maskinnedbrud, hvilket er kritisk ved højt output. Risiko for kopiprodukter, hvor design kopieres og sælges billigere. Arbejdsmarkedstrusler, som strejker, mangel på personale eller lav arbejdskrafttilgængelighed. Arbejdsskader, der kan føre til sygefravær, mindre kapacitet og øgede omkostninger. Ophør af lejemål eller huslejestigninger, som kan tvinge virksomheden til at flytte produktionen med store omkostninger og potentielt produktionsstop. Mangel på efterspørgsel, hvis markedet ændrer sig eller nye konkurrenter kommer til.
A8: Gantt kort
A9: Projekt planlæggelse
A10: Projektets startdato: | B10: 45964
A11: Projektets slutdato: | B11: 46002
A12: Beskrivelse af opgaver | B12: Dato for undervisning | C12: Dato for start på opgaven | D12: Afsluttelse af opgaven | E12: 45964 | F12: 45965 | G12: 45966 | H12: 45967 | I12: 45968 | J12: 45971 | K12: 45972 | L12: 45973 | M12: 45974 | N12: 45975 | O12: 45978 | P12: 45979 | Q12: 45980 | R12: 45981 | S12: 45982 | T12: 45985 | U12: 45986 | V12: 45987 | W12: 45988 | X12: 45989 | Y12: 45992 | Z12: 45993 | AA12: 45994 | AB12: 45995 | AC12: 45996 | AD12: 45999 | AE12: 46000 | AF12: 46001 | AG12: 46002
A14: Projektplan & risikovurdering | B14: 45978 | C14: 45978 | D14: 46001
A15: Interessantanalyse &kommunikationsplan | B15: 45982 | C15: 45982 | D15: 45989
A16: Organisation & arbejdsopgaver | B16: 45964 | C16: 45964 | D16: 45967
A17: Stykliste | B17: 45964 | C17: 45964 | D17: 45965
A18: Forsyningsstrategi | B18: 45965 | C18: 45965 | D18: 45994
A19: Operationsdiagram | B19: 45965 | C19: 45965 | D19: 45967
A20: Maskinliste & fremstillingsvalg | B20: 45964 | C20: 45966 | D20: 45987
A21: Faciliteter & layout | B21: 45978 | C21: 45992 | D21: 45996
A22: Procesanalyse & operationskort | B22: 45978 | C22: 45978 | D22: 45992
A23: Produktionsplan & vedligehold | B23: 45980 | C23: 45992 | D23: 45996
A24: MRP | B24: 45979 | C24: 45980 | D24: 45982
A25: Lagerstyring | B25: 45992 | C25: 45994 | D25: 46001
... A28: Investeringsrentabilitet | B28: 45992 | C28: 45996 | D28: 46001

Sheet 2 Interessentanalyse & kom.plan
B3: Interessentanalyse | L3: Kommunikationsplan for et statusmøde
B4: Høj | J4: Direktør | L4: Interessents Navn | M4: Budskab/indhold | N4: Kommunikations Format | O4: Anvendte Medie | P4: Ønsket Effekt | Q4: Ansvar
I5: Bogholderi | J5: HR | L5: Ledelse | M5: Hvordan ser det hele ud, er der noget der skal ændres? | N5: Fysiske møder | O5: Mails | P5: sammenhæng mellem hele virksomheden | Q5: Høj
I6: Logistik | J6: Indkøbs-styring | L6: Produktion | M6: Kører produktionen som den skal? | N6: Fysiske møder | O6: Mails/telefon | P6: God produktion | Q6: Høj
B7: Magt | J7: Kvalitets-sikring | L7: Kunder | M7: Er kunderne tilfredse? | N7: Digitalt | O7: Mails/telefon | P7: Tillid | Q7: Høj
J8: Montage | L8: Logistik | M8: Glider det hele som det skal, eller skal der ændres noget? | N8: Mails/Møder (Fysisk/digitalt) | O8: Mails/Telefon | P8: Glidende logistik, så produktonen ikke går i stå | Q8: Høj
I9: Fremstilling | J9: Design | L9: Fagforenigerne/ Overenskomst | M9: Kan vi gøre arbejdspladsen bedre? | N9: Mails | O9: Mails/Telefon | P9: Rettigheder, vilkår, samarbejde | Q9: Høj
I10: Test/prototyping | J10: Lager (produktion) | L10: Leverandør | M10: Kører det hele som det skal? | N10: Digitalt | O10: Mails | P10: Få ting til at komme til den rette tid | Q10: Høj
B11: Lav | I11: CAD/CAE | J11: Lager(Varemodtagelse) | L11: Økonomi | M11: Laver vi overskud eller underskud. Er der noget vi kan gøre bedre? | N11: Fysiske møder | O11: Mails | P11: Sund økonomi | Q11: Høj
C12: Lav | F12: Interesse | J12: Høj | L12: Produdvikling | M12: Er der nogle nye produkter, der er ved at være klar til produktion? | N12: Fysiske møder | O12: Mails | P12: Fremme udviklinger på produktet | Q12: Medium/høj
L13: HR | M13: Er medarbejderne glade? | N13: Fysiske møder | O13: Mails/Telefon | P13: Trivsel | Q13: Høj
B15: Interessentanalyse oversigt
B16: Direktør | D16: Direktøren er den der har højst interesse og højst magt.
B17: HR | D17: HR er bindeleddet mellem medarbejderne og ledelsen. Deres interresse er derfor høj og magt er også høj.
B18: Bogholderi | D18: Bogholderi håndterer virksomhedens økonomiske registreringer. Deres interesse er høj og magt er også høj. | M18: 7
B19: Indkøbsstyring | D19: De planlægger, bestiller og styrer virksomhedens indkøb. Deres interesse er derfor høj, men de har ikke højere magt end HR og bogholderi.
B21: Logistik | D21: Logistik har lige meget magt som indkøbsstyring har og lige meget interesse.
B22: Lager | D22: Lager i varemodtagelsen har høj interesse, men ingen magt.
B24: Design | D24: Design har høj interesse, men næsten ingen magt.
B25: Test og prototyping | D25: Test og prototyping har høj interesse og høj magt, da de tester nye produkter.
B26: CAD/CAE | D26: CAD/CAE har høj interesse, men ingen magt.
B28: Montage | D28: Montage har høj interresse, og middel magt.
B29: Lager | D29: Lager i produktionen har har høj interesse, men ingen magt.
B30: Kvalitetssikring | D30: Kvalitetssikring har høj interesse og høj magt.
B31: Fremstilling | D31: Fremstilling har høj interesse, men ikke særlig høj magt.

Sheet 3 Organisation & arbejdsopg.
B4: Organisations diagram
B28: Arbejdsopgaver
B30: Direktør | D30: Direktøren har mest autoritet og tager alle endelige beslutninger 1 ansat til 55.000 kr. | K30: 1
B31: HR | D31: HR er bindeleddet mellem medarbejderne og ledelsen. Deres arbejdsopgaver er rekruttering, onboarding, udviklng, trivsel, løn, jura, samtaler, strategi, offboarding.
B33: Bogholderi | D33: Bogholderi håndterer virksomhedens økonomiske registreringer og sikrer, at alle indtægter, udgifter og bilag bliver korrekt bogført. 1 er ansat til HR og bogholderi til 45.000 kr. | K33: 1
B34: Indkøbsstyring | D34: De planlægger, bestiller og styrer virksomhedens indkøb af materialer, varer og leverandører – så produktionen altid har det, der skal bruges, til den bedste pris og tid.
B36: Logistik | D36: De planlægger, styrer og optimerer transport, lager, materialeflow og distribution, så varer kommer det rigtige sted hen på det rigtige tidspunkt. 1 er ansat til indkøbsstyring og logistik til 40.000 kr. | K36: 1
B37: Lager | D37: De modtager, kontrollerer, registrerer og placerer varer korrekt på lageret, når de ankommer til virksomheden. 2 er ansat til 28.000 kr. Pr. Medarbejder | K37: 2
B39: Design | D39: Design designer nye produkter og videreudvikler eksiterende produkter 2 er ansat til 35.000 kr. Pr. medarbejder og begge laver både design, test og prototyping og CAD/CAE. | K39: 2
B40: Test og prototyping | D40: De laver mockups og prototyper af de nye produkter, hvor de laver styrkeberigninger og tests på dem.
B41: CAD/CAE | D41: De laver digitale tegninger af de nye designs.
B43: Montage | D43: De samler produktets dele til et færdigt produkt – enten manuelt eller ved hjælp af maskiner. 6 er ansat så, så der kan være 3 på hvert hold. Dagsholdet får 30.000 kr. og aftenholdet får 35.000 kr. | K43: 6
B44: Lager | D44: Lager har kontrol over hvad og hvor meget vi har på lager, hvilket hjælper os med at spare på bestilling af nye vare. 4 er ansat, så 2 kan være på hvert hold. Dagshold får 28.000 kr. og aftenholdet får 30.000 kr. | K44: 4
B45: Kvalitetssikring | D45: At sikre, at produkter eller processer lever op til krav og standarder, så fejl opdages og forebygges. Dette tager produktionsmedarbejderne sig af.
B46: Fremstilling | D46: De producerer produktet ud fra materialer og komponenter ved hjælp af maskinerne. 22 er ansat, så der er 11 på hvert hold. Dagsholdet får 30.000 kr. Aftenholdet får 35.000 kr. | K46: 22
B47: Antal ansatte | C47: =SUM(K30:K46) -> 39 | I47: Løn pr. måned | J47: =40000+28000+28000+70000+90000+115000+56000+60000+33000+330000+385000 -> 1235000

Sheet 4 Stykliste
B4: Stykliste
B5: PART NO. | C5: PART | D5: Description | E5: Material | F5: Quantity
B6: 10-200 | C6: #VALUE! | D6: Sæde | E6: Plywood | F6: 1
B7: 10-100 | C7: #VALUE! | D7: Stel | E7: 1023 Carbon steel | F7: 1
B8: 1001 | C8: #VALUE! | D8: Indsats i sæde | E8: AISI Type 316L Stainless steel | F8: 4
B9: 1003 | C9: #VALUE! | D9: Spacer | E9: POM | F9: 8
B10: 1005 | C10: #VALUE! | D10: Pluks | E10: PP | F10: 4
B11: 1006 | C11: #VALUE! | D11: Indsats i fod | E11: AISI 316 Annealed Stainless steel bar (SS) | F11: 4
B12: 1004 | C12: #VALUE! | D12: Fod | E12: PP | F12: 4
B13: 1002 | C13: #VALUE! | D13: Skrue | E13: Cast Satinless steel M5 x 30mm | F13: 4

Sheet 5 Forsyningsstrategi
A1: Stykliste
A2: PART NO. | B2: PART | C2: Description | D2: Material | E2: Quantity
A3: 10-200 | B3: #VALUE! | C3: Sæde | D3: Plywood | E3: 1
A4: 10-100 | B4: #VALUE! | C4: Stel | D4: 1023 Carbon steel | E4: 1
A5: 1001 | B5: #VALUE! | C5: Indsats i sæde | D5: AISI Type 316L Stainless steel | E5: 4
A6: 1003 | B6: #VALUE! | C6: Spacer | D6: POM | E6: 8
A7: 1005 | B7: #VALUE! | C7: Pluks | D7: PP | E7: 4
A8: 1006 | B8: #VALUE! | C8: Indsats i fod | D8: AISI 316 Annealed Stainless steel bar (SS) | E8: 4
A9: 1004 | B9: #VALUE! | C9: Fod | D9: PP | E9: 4
A10: 1002 | B10: #VALUE! | C10: Skrue | D10: Cast Satinless steel M5 x 30mm | E10: 4
A12: Maskine pris
A13: Enhed | C13: Kr/t | D13: Enheder/t | E13: Styk pris eksl. Materiale | F13: Styk pris inkl. Materieale | G13: Antal | H13: Total for 2000 stole
A14: Indsats til sæde | C14: =D70 -> 495.26912 | D14: 144 | E14: =C14/D14 -> 3.4393689 | F14: =E14+F21 -> 5.4518689 | G14: 8000 | H14: =F14*G14 -> 43614.951
A15: Stel | C15: =D84+D98+D112+D127 -> 1275.8648 | D15: 130 | E15: =C15/D15 -> 9.8143444 | F15: =E15+F22 -> 235.64768 | G15: 2000 | H15: =(F15*G15) -> 471295.36 | Q15: https://staalet.dk/vare/rundt-staalroer/
A16: Sæde | C16: =D144+D158+D172+D186+D200+D214 -> 790.54889 | D16: 30 | E16: =C16/D16 -> 26.35163 | F16: =E16+F23 -> 67.60163 | G16: 2000 | H16: =F16*G16 -> 135203.26 | Q16: https://www.stark.dk/raw-fyr-krydsfiner-a-c-12-mm-1220-mm-2440-mm?id=3200-9590207
A17: Total | C17: =D70+D84+D98+D112+D144+D158+D172+D186+D127 -> 2311.5722 | E17: =E14+E15+E16 -> 39.605343 | F17: =SUM(F14:F16) -> 308.70118 | H17: =SUM(H14:H16)*1.1 -> 715124.92
A19: Materiale pris
A20: Enhed | B20: Materiale | C20: Størrelse | D20: Antal pr størrelse | E20: Kr. | F20: Kr. pr. enhed | G20: Antal | H20: Total
A21: Indsats til sæde | B21: Rustfri stål | C21: Ø20x3000mm | D21: =3000/14 -> 214.28571 | E21: =575*0.75 -> 431.25 | F21: =E21/D21 -> 2.0125 | G21: 8000 | H21: =(G21*F21) -> 16100
A22: Stel | B22: aisi 1045 | C22: Ø16x6000mm | D22: =5400/6000 -> 0.9 | E22: =271*0.75 -> 203.25 | F22: =E22/D22 -> 225.83333 | G22: 2000 | H22: =(F22*G22) -> 451666.67
A23: Sæde | B23: Krydsfiner | C23: 1220x2440mm | D23: 9 | E23: =495*0.75 -> 371.25 | F23: =E23/D23 -> 41.25 | G23: 2000 | H23: =(G23*F23) -> 82500
A24: Lim | B24: DANA lim | C24: 15L | D24: =15000/167 -> 89.820359 | E24: =2050*0.75 -> 1537.5 | F24: =E24/D24 -> 17.1175 | G24: 2000 | H24: =F24*G24 -> 34235
A25: Maling | B25: RAL9005 | C25: 3000ml | D25: =3000/'12 MRP'!F9 -> 17.574692 | E25: =659*0.75 -> 494.25 | F25: =E25/D25 -> 28.122825 | G25: 2000 | H25: =G25*F25 -> 56245.65
A26: Total | E26: =SUM(E21:E25) -> 3037.5 | F26: =SUM(F21:F23) -> 269.09583 | H26: =SUM(H21:H25)*1.1 -> 704822.05
A29: Komponenter
A30: Enhed | B30: Materiale | C30: Pris pr. stk. | D30: Pris pr. enhed | E30: Antal | F30: Total
A31: Split til fod | B31: aisi 1020 steel | C31: 4.5 | D31: =C31*4 -> 18 | E31: 32000 | F31: =E31*C31 -> 144000
A32: Fod | B32: PP | C32: 1.2 | D32: =C32*4 -> 4.8 | E32: 32000 | F32: =E32*C32 -> 38400
A33: Plug til fod | B33: PP | C33: 1.2 | D33: =C33*4 -> 4.8 | E33: 32000 | F33: =E33*C33 -> 38400
A34: Spacer | B34: POM | C34: 1.5 | D34: =C34*8 -> 12 | E34: 64000 | F34: =C34*E34 -> 96000
A35: Skrue | B35: Cast iron steel | C35: 0.5 | D35: =C35*4 -> 2 | E35: 32000 | F35: =E35*C35 -> 16000
A36: Total | D36: =SUM(D31:D35) -> 41.6 | F36: =SUM(F31:F35) -> 332800
A39: El pris /år
A40: =C65+C79+C93+C107+C122+C139+C153+C167+C181+C195+C209 -> 560688.5
A44: Krajlics model
A45: Høj | B45: volumevarer | F45: Strategisk varer
C46: Finér til sæde | D46: Rør til stel
D47: Rør til indsats I sæde | F47: Maling
A48: vigtigheden af indkøb | C48: Lim
B49: Ukritiske varer | F49: Flaskehalsvarer
D50: Skrue | F50: Indsats i fod
D51: Spacer | E51: Pluks
A52: Lav | D52: Fod
B53: Lav | E53: Kompleksitet af leverendørmarkedet | I53: Høj
A58: Indsats til sæde | B58: cnc drejebænk
B59: Input data | C59: yearly rate | D59: Hourly rate
A60: Acquistion price incl. Equipment | B60: 400000
A61: Internal rate of interest | B61: 0.07 | C61: =B60*B61 -> 28000 | D61: =C61/B64 -> 38.781163
A62: Depreciation (years) | B62: 30 | C62: =B60/B62 -> 13333.333 | D62: =C62/8765 -> 1.5212017
A63: Rent (kr/m2/year) | B63: 250 | C63: =B63*12 -> 3000 | D63: =C63/B64 -> 4.1551247
A64: Operation hours pr. year (2 shifts) | B64: 722
A65: Energy consumption (kr pr/year) | B65: 63 | C65: =B65*B64 -> 45486 | D65: =C65/B64 -> 63
A66: Maintenance (kr pr/year) | B66: 0.05 | C66: =B66*B60 -> 20000 | D66: =C66/B64 -> 27.700831
A67: Consumables (kr pr/year) | B67: 150000 | C67: =B67 -> 150000 | D67: =C67/B64 -> 207.75623
A68: Machine tools (kr pr/year) | B68: 100000 | C68: =B68 -> 100000 | D68: =C68/B64 -> 138.50416
A69: Auxiliary tools (kr pr/year) | B69: 10000 | C69: =B69 -> 10000 | D69: =C69/B64 -> 13.850416
A70: Total | C70: =SUM(C61:C69) -> 369819.33 | D70: =SUM(D61:D69) -> 495.26912
A72: CNC Rør bukker
B73: Input data | C73: yearly rate | D73: Hourly rate
A74: Acquistion price incl. Equipment | B74: 250000
A75: Internal rate of interest | B75: 0.07 | C75: =B74*B75 -> 17500 | D75: =C75/B78 -> 60.763889
A76: Depreciation (years) | B76: 20 | C76: =B74/B76 -> 12500 | D76: =C76/B77 -> 20.833333
A77: Rent (kr/m2/year) | B77: 600 | C77: =B77*12 -> 7200 | D77: =C77/B78 -> 25
A78: Operation hours pr. year (2 shifts) | B78: 288
A79: Energy consumption (kr pr/year) | B79: ='7 Maskinliste & fremstil.valg'!L8*2.5 -> 15 | C79: =B79*B78 -> 4320 | D79: =C79/B78 -> 15
A80: Maintenance (kr pr/year) | B80: 0.05 | C80: =B80*B74 -> 12500 | D80: =C80/B78 -> 43.402778
A81: Consumables (kr pr/year) | B81: 10000 | C81: =B81 -> 10000 | D81: =C81/B78 -> 34.722222
A82: Machine tools (kr pr/year) | B82: 50000 | C82: =B82 -> 50000 | D82: =C82/B78 -> 173.61111
A83: Auxiliary tools (kr pr/year) | B83: 10000 | C83: =B83 -> 10000 | D83: =C83/B78 -> 34.722222
A84: Total | C84: =SUM(C75:C83) -> 124020 | D84: =SUM(D75:D83) -> 408.05556
A86: svjeser
B87: Input data | C87: yearly rate | D87: Hourly rate
A88: Acquistion price incl. Equipment | B88: 600000
A89: Internal rate of interest | B89: 0.07 | C89: =B88*B89 -> 42000 | D89: =C89/B92 -> 60.606061
A90: Depreciation (years) | B90: 12 | C90: =B88/B90 -> 50000 | D90: =C90/B91 -> 83.333333
A91: Rent (kr/m2/year) | B91: 600 | C91: =B91*12 -> 7200 | D91: =C91/B92 -> 10.38961
A92: Operation hours pr. year (2 shifts) | B92: 693
A93: Energy consumption (kr pr/year) | B93: ='7 Maskinliste & fremstil.valg'!L9*2.5 -> 35 | C93: =B93*B92 -> 24255 | D93: =C93/B92 -> 35
A94: Maintenance (kr pr/year) | B94: 0.05 | C94: =B94*B88 -> 30000 | D94: =C94/B92 -> 43.290043
A95: Consumables (kr pr/year) | B95: 10000 | C95: =B95 -> 10000 | D95: =C95/B92 -> 14.430014
A96: Machine tools (kr pr/year) | B96: 50000 | C96: =B96 -> 50000 | D96: =C96/B92 -> 72.150072
A97: Auxiliary tools (kr pr/year) | B97: 10000 | C97: =B97 -> 10000 | D97: =C97/B92 -> 14.430014
A98: Total | C98: =SUM(C89:C97) -> 223455 | D98: =SUM(D89:D97) -> 333.62915
A100: Laser Skære/bore
B101: Input data | C101: yearly rate | D101: Hourly rate
A102: Acquistion price incl. Equipment | B102: 700000
A103: Internal rate of interest | B103: 0.07 | C103: =B102*B103 -> 49000 | D103: =C103/B106 -> 61.25
A104: Depreciation (years) | B104: 25 | C104: =B102/B104 -> 28000 | D104: =C104/B105 -> 112
A105: Rent (kr/m2/year) | B105: 250 | C105: =B105*12 -> 3000 | D105: =C105/B106 -> 3.75
A106: Operation hours pr. year (2 shifts) | B106: 800
A107: Energy consumption (kr pr/year) | B107: ='7 Maskinliste & fremstil.valg'!L10*2.5 -> 12.5 | C107: =B107*B106 -> 10000 | D107: =C107/B106 -> 12.5
A108: Maintenance (kr pr/year) | B108: 0.05 | C108: =B108*B102 -> 35000 | D108: =C108/B106 -> 43.75
A109: Consumables (kr pr/year) | B109: 10000 | C109: =B109 -> 10000 | D109: =C109/B106 -> 12.5
A110: Machine tools (kr pr/year) | B110: 50000 | C110: =B110 -> 50000 | D110: =C110/B106 -> 62.5
A111: Auxiliary tools (kr pr/year) | B111: 10000 | C111: =B111 -> 10000 | D111: =C111/B106 -> 12.5
A112: Total | C112: =SUM(C103:C111) -> 195000 | D112: =SUM(D103:D111) -> 320.75
A115: Afgrater
B116: Input data | C116: yearly rate | D116: Hourly rate
A117: Acquistion price incl. Equipment | B117: 90000
A118: Internal rate of interest | B118: 0.07 | C118: =B117*B118 -> 6300 | D118: =C118/B121 -> 21.875
...

Sheet 6 Operationsdiagram
B3: Operationsdiagram
C5: Indsats i sæde | F5: Sæde | J5: Stel
H49: Spacer
H50: Skrue
H74: Pluks
H75: Indsats i fod
H76: Fod

Sheet 7 Maskinliste & fremstil.valg
A1: Billede | B1: Maskinliste
A2: Titel
A3: Kontrolleret | B3: initialer | F3: Oprettet den | G3: dato | M3: Revisionsnr. | N3: nummer
A4: Forfatter | B4: initialer | F4: Ansvarlig | G4: initialer | M4: Ændret den | N4: dato
A5: Maskine ID | B5: Maskinnavn | C5: Producent | D5: Model # | E5: Serienummer | G5: Funkion | H5: Proces # | I5: Specfikationer | J5: Dimensioner | K5: Vedligeholdelsesplan | L5: Energiforbrug | M5: Produktionsstørrelse | N5: Købsdato | O5: Indkøbspris DKK | P5: Levetid | Q5: Afskrivningsværdi | R5: Dokumentation | S5: Maskinnummer:
A6: Enhed | K6: Måneder | L6: kWh | M6: Pr. Time | P6: år
B7: CNC Drejebænk | C7: Maier | D7: MLK 32 D Proline | E7: MLK32D-F-2025-EDU-009 | G7: Lave indsats til sæde | I7: Ø32mm 6000 rpm | J7: 160x230x200cm | K7: 4 | L7: 25 | M7: 144 | O7: 400000 | P7: 30 | R7: https://www.exapro.com/maier-mlk-32-d-proline-p230314034/?utm_source=chatgpt.com | S7: 108
B8: CNC Rør bukker | C8: Herber | D8: 127 CNC | E8: HERBER127-SHOP-019 | G8: Bukkemaskine til rør | I8: Ø127mm max bukkevinkel 182 grader | J8: 700x 220x180 | K8: 3 | L8: 6 | M8: 360 | O8: 250000 | P8: 20 | R8: https://www.machineseeker.dk/herber-127+cnc/i-17699608 | S8: 203
B9: CoWelder | C9: Cowelder | D9: PI TIG 350 AC/DC | E9: PITIG350-FIK-20251125-003 | G9: Svejse stel sammen | I9: rækkevidde 850mm max 8kg | J9: 980x545x1090mm | K9: 3 | L9: 14 | M9: 150 | O9: 600000 | P9: 12 | R9: https://www.migatronic.com/da/produkter-og-loesninger/svejsemaskiner/cowelder/ | S9: 204
B10: Skære/bore | C10: bodor | D10: T-Trans | E10: BDTRANS-SN-2025-011 | G10: laser skære + bore til stel | I10: max 100mm | J10: 12900x2370x2650mm | K10: 3 | L10: 5 | M10: 130 | O10: 700000 | P10: 25 | R10: https://bodor.com/en/fiber-laser-cutting-machine/tube-laser-cutting-machines/t.html | S10: 201
B11: CNC Skærer | C11: biesse | D11: Rover K Smart 1532 | E11: 84547 | G11: CNC skære til sæde | I11: Max arbejdsplads 3200x1560x165mm 24000 rpm | J11: 6750x4520x2400mm | K11: 3 | L11: 29 | M11: 30 | O11: 340000 | P11: 15 | R11: https://www.hoechsmann.com/en/article/84547/biesse_rover_k_smart_1532 | S11: 101
B12: Open glue spreader | C12: OMMA | D12: OPEN | E12: OMMA-OPN-25A-0002 | G12: Påføring af lim på plader | I12: Brede 1400-3100mm tykelse 80mm | J12: 3400x1700x1300mm | K12: 1 | L12: 5 | M12: 40 | O12: 370000 | P12: 10 | R12: https://www.omma.com/en/products/p/open-glue-spreader | S12: 102
A13: 79650 | B13: Rover A Smart 1632 | C13: Biesse | D13: Rover K Smart 1632 (5 akset CNC router) | E13: ROV-K1632-INST-0012 | G13: Fræsning og boring | I13: 3280x1620mm | J13: 10700x6400x2700 mm | K13: 2 | L13: 13 | M13: 60 | O13: 600000 | P13: 12 | R13: https://www.hoechsmann.com/en/article/79653/biesse_rover_a_smart_1632 | S13: 105
A14: powder coating line | B14: Spray Paint System Powder Coating | C14: Yantai Lingyu Machinery Co., Ltd | D14: High Quality Spray Paint System Powder Coating Production Line | E14: LYM-SPRAYLINE-2025-CN-0042 | G14: Male sædet | I14: 600x600x500mm | J14: 72m2 | K14: 3 | L14: 15 | M14: 35 | O14: 1615665 | P14: 15 | R14: https://lingyumachinery.en.made-in-china.com/product/hwaAVTmcYtkZ/China-High-Quality-Spray-Paint-System-Powder-Coating-Production-Line-for-Manufacture-Wooden-Furniture-and-Chair.html?pv_id=1jatismome92&faw_id=1jatjhlvc3e3&bv_id=1jatjhlve51d&pbv_id=1jatislbc1f5 | S14: 107
A15: OD120 | B15: Tube End Deburring Machine | C15: NS Máquinas Industriais, Lda. | D15: OD120 | E15: NSM-OD120-2025-PT-0008 | G15: Afgrate rør | I15: Ø 10-120mm | J15: 1140x670x1400mm | K15: 4 | L15: 3.5 | M15: 360 | O15: 90000 | P15: 20 | R15: https://nsmaquinas.com/product/od120-od160-tube-end-deburring-machines | S15: 202
B16: QuickWood QT4 – 4-Sided Curved Part Sanding Machine | C16: QuickWood Systems A/S | D16: QT4 | E16: QT4-2023-0147 | G16: Pudse sædet | I16: 500*600*400mm | J16: 1400x1200x1500mm | K16: 3 | L16: 2 | M16: 80 | O16: 224115 | P16: 10 | R16: https://quickwood.com/collections/curved-parts-sanding/products/qt4-4-sided-curved-part-sanding | S16: 106
B17: Press Machine for Chair Seats | C17: SAGA Machinery Co | D17: YX80‑SA | E17: SAGA-HF-2025-0058 | G17: Støbe sædet | I17: 1600x800mm | J17: 2300x800x2200mm | K17: 3 | L17: 15 | M17: 35 | O17: 155000 | P17: 15 | R17: https://sagahf.en.made-in-china.com/product/GFKaARpJBUYn/China-Press-Machine-for-Chair-Seats-and-Backs-Plywood-Curved-Gluing-Press.html | S17: 104
B18: Lay up table | C18: Evans Midwest | D18: Evans Midwest 4283 Lay-Up-bord | E18: 4283 Model HPL | G18: Tørre sæderne efter lim | J18: 2000x4000x1000 | K18: 4 | L18: 0 | M18: 35 | O18: 153636 | P18: 25 | R18: https://360degreemachinery.com/shop/categories-machine-type/laminate-slitters/evans-midwest-4283-lay-up-table/ | S18: 103
N19: I alt: | O19: =SUM(O7:O18) -> 5498416
B24: Fremstillingsvalg
B25: Da materialerne allerede var givet, har vi fokuseret på selve produktionen. Stellet bliver lavet af stålrør, som bukkes og svejses for at opnå den rigtige form og styrke. Sædet er lavet af krydsfiner, som formes, så det får den korrekte kurve. Indsatsen fremstilles på en CNC-drejebænk for at sikre præcision og ensartethed i serieproduktionen.

Sheet 8 Faciliteter & layout
B2: plan layout
C4: Lager/opbevering af færige stole
C6: Prduktions linje for sæde
C8: Prduktions linje for stel
C10: Personale rum
C12: samle område for stol
C14: pakke område
C16: pile fra Lager igenem sæde produktion til smaling | AA16: https://www.edc.dk/erhverv/erhvervslejemaal/lager-produktion/6705-esbjerg-oe/spangsbjerg-moellevej-100/670114509/
C18: pile fra Lager igenem stel produktion til smaling
C20: indelvering af være/rå matriale
C22: stol fra same område til opbevaring også til pakke område og efter til udlevering
BJ74: 1

Sheet 9 Procesanalyse&Operationskort
B2: Operationskort | J2: PROCESANALYSE - Stel
F3: Tegningsnummer: | G3: Komponentnavn:
B4: Indgående materiale: | F4: 0001-000 | G4: Stel | J4: SAG | K4: Elementrækkehus 1234567
B5: Ø 16 mm stangmateriale, varenummr 10-100 | J5: Emne | K5: Produktion af vare nr. 10-100
J6: Område | K6: Dette operationsmønsterskema er på et område, som udgør xxx m² | Z6: SAMLEVEJLEDNING
B7: Proces-nummer: | E7: Maskinnavn: | F7: Maskinnummer: | G7: Proces: | H7: Estimeret | J7: Dato
H8: Styk/time | J8: Navn
D9: 1+2 | E9: CNC sav + bor | F9: 201 | G9: Afsave og bore | H9: 130
D10: 3 | E10: Tube End Deburring Machine | F10: 202 | G10: Afgrate | H10: 360
D11: 4 | E11: CNC Rør bukker | F11: 203 | G11: Bukke | H11: 34 | K11: AKTIVITETER | L11: Operation | M11: Håndtering | N11: Transport | O11: Kontrol | P11: Ophold | Q11: Lager | R11: Arbejdstid | S11: Maskintid | T11: Afstand | U11: Mængde | V11: Bemærkning
D12: 5 | E12: CoWelder | F12: 204 | G12: Svejse | H12: 90 | J12: Akt. Nr. | R12: min. | T12: m.
J13: 1 | K13: Modtagelse af rør | R13: 10 | U13: Ø16*6000 mm | V13: Gange 30
B14: Operationskort | J14: 2 | K14: Modtagekontrol, kontrol om korrekt levering samt fejl på de indgående materialer. | R14: 10
F15: Tegningsnummer: | G15: Komponentnavn:
B16: Indgående materiale: | F16: 0002-000 | G16: Sæde | J16: 3 | K16: Rørene bliver transporteret til CNC sav + bor | R16: 15 | T16: 17.88
B17: xx mm træfinér, varenummer 10-200 | J17: 4 | K17: Rørene bliver afsavet, boret og målt | S17: 14
J18: 5 | K18: Rørene bliver transporteret til tube end deburring machine | R18: 10 | T18: 2.46
B19: Proces-nummer: | E19: Maskinnavn: | F19: Maskinnummer: | G19: Proces: | H19: Estimeret | J19: 6 | K19: Rørene bliver afgratet | S19: 5
H20: Styk/time | J20: 7 | K20: Rørene bliver transporteret til rør bukker | R20: 10 | T20: 2.55
D21: 6 | E21: CNC- Skærer | F21: 101 | G21: Skære | H21: 30 | J21: 8 | K21: Rørene bliver bukket | S21: 53
D22: 7 | E22: Open glue spreader | F22: 102 | G22: Lime | H22: 40 | J22: 9 | K22: Rørene bliver transporteret til coWelder | R22: 15 | T22: 2.49
D23: 8 | E23: Tørrebord | F23: 103 | G23: Tørre sæderne | H23: 40 | J23: 10 | K23: Rørene bliver svejset | S23: 20
D24: 9 | E24: Press Machine for Chair Seats | F24: 104 | G24: Presse | H24: 35 | J24: 11 | K24: Kontrol af færdige produkt | R24: 10
D25: 10+11 | E25: Rover A Smart 1632 | F25: 105 | G25: Fræse og bore | H25: 60
D26: 12 | E26: QuickWood QT4 – 4-Sided Curved Part Sanding Machine | F26: 106 | G26: Pudse | H26: 80 | J26: Sum maskintid (min.) | S26: =SUM(S13:S24) -> 92
D27: 13+14 | E27: Spray Paint System Powder Coating | F27: 107 | G27: Male | H27: 35 | J27: Sum arbejdstid (min.) | R27: =SUM(R13:R24) -> 80
J28: Sum Produktion tid (min.) | Q28: =SUM(S26+R27) -> 172
B31: Operationskort | J31: PROCESANALYSE - Sæde
F32: Tegningsnummer: | G32: Komponentnavn:
B33: Indgående materiale: | F33: 0003-000 | G33: Indsats i sæde | J33: SAG | K33: Elementrækkehus 1234567
B34: Ø ?? stangmateriale, varenummer 1001 | J34: Emne | K34: Produktion af vare nr. 10-200
J35: Område | K35: Dette operationsmønsterskema er på et område, som udgør xxx m²
B36: Proces-nummer: | E36: Maskinnavn: | F36: Maskinnummer: | G36: Proces: | H36: Estimeret | J36: Dato
H37: Styk/time | J37: Navn
D38: 15+16 | E38: CNC-drejebænk | F38: 108 | G38: Dreje + skære | H38: 144
K40: AKTIVITETER | L40: Operation | M40: Håndtering | N40: Transport | O40: Kontrol | P40: Ophold | Q40: Lager | R40: Arbejdstid | S40: Maskintid | T40: Afstand | U40: Mængde | V40: Bemærkning
J41: Akt. Nr. | R41: min. | T41: m.
J42: 1 | K42: Modtagelse af finér | R42: 10 | U42: 1220x2440mm | V42: Gange 30
J43: 2 | K43: Modtagelse af lim og maling | R43: 5 | U43: 167 ml lim og 170,7 ml maling | V43: Gange 30
J44: 3 | K44: Modtagekontrol, kontrol om korrekt levering samt fejl på de indgående materialer. | R44: 10
J46: 4 | K46: Finéren bliver transporteret til CNC-skærer | R46: 2 | T46: 22.54
J47: 5 | K47: Finéren bliver skåret | S47: 60
J48: 6 | K48: Finéren bliver transporteret til open glue spreader | R48: 15 | T48: 5.32
J50: 7 | K50: Finéren bliver limet sammen | S50: 45
J51: 8 | K51: Finéren bliver transporteret til tørrebord | R51: 15 | T51: 4.55
J52: 9 | K52: Finéren tørrer | S52: 45
J53: 10 | K53: Finéren bliver transporteret til presser | R53: 15 | T53: 3.31
J54: 11 | K54: Finéren bliver presset sammen til sæde | S54: 51.5
J55: 12 | K55: Sædet bliver transporteret til Rover A Smart 1632 | R55: 10 | T55: 3.45
J56: 13 | K56: Sædet bliver skåret til og der bliver boret huller | S56: 30
J57: 14 | K57: Kontrol af sæde | R57: 10
J58: 15 | K58: Sædet bliver transporteret til Quickwood QT4 | R58: 10 | T58: 3.49
J59: 16 | K59: Sædet bliver pudset | S59: 22.5
J60: 17 | K60: Sædet bliver transporteret til Spray paint system | R60: 10 | T60: 6.67
J61: 18 | K61: Sædet bliver malet og tørret | S61: 51.5
J62: 19 | K62: Kontrol af færdige produkt | R62: 10
J64: Sum maskintid (min.) | S64: =SUM(S42:S62) -> 305.5
J65: Sum arbejdstid (min.) | R65: =SUM(R42:R62) -> 122
J66: Sum Produktion tid (min): | Q66: =SUM(S64+R65) -> 427.5
J70: PROCESANALYSE - Indsats i sæde
J72: SAG | K72: Elementrækkehus 1234567
J73: Emne | K73: Produktion af vare nr. 1001
J74: Område | K74: Dette operationsmønsterskema er på et område, som udgør xxx m²
J75: Dato
J76: Navn
K79: AKTIVITETER | L79: Operation | M79: Håndtering | N79: Transport | O79: Kontrol | P79: Ophold | Q79: Lager | R79: Arbejdstid | S79: Maskintid | T79: Afstand | U79: Mængde | V79: Bemærkning
J80: Akt. Nr. | R80: min. | T80: m.
J81: 1 | K81: Modtagelse af rør | R81: 10 | U81: Ø20x3000mm | V81: Gange 30
J82: 2 | K82: Modtagekontrol, kontrol om korrekt levering samt fejl på de indgående materialer. | R82: 10
J84: 3 | K84: Rørene bliver transporteret til CNC drejebænk | R84: 10 | T84: 71.23
J85: 4 | K85: Rørene bliver drejet og skåret | S85: 12.5
J86: 5 | K86: Kontrol af færdige produkt | R86: 10
J88: Sum maskintid (min.) | S88: =SUM(S81:S86) -> 12.5
J89: Sum arbejdstid (min.) | R89: =SUM(R81:R86) -> 40
J90: Sum Produktion tid (min.) | Q90: =SUM(S88+R89) -> 52.5

Sheet 10 Prod.plan&vedligehold
A2: vedligehold
A3: Maskine | B3: udføres af | C3: del | D3: komplikationer | E3: vedligeholdelse | F3: Skiftes | G3: rengøring | H3: rengøring min | I3: Estimeret årlig vedligeholdelsespris
A4: CNC Drejebænk – MLK 32 D Proline | B4: Operatør | C4: Spindel, føringer, kølevæske system | D4: Risiko for unøjagtighed ved dårlig smøring | E4: Smøring hver måned, kalibrering hver 6. måned | F4: Kølevæske hver 3. måned | G4: Fjern spåner, tør overflader | H4: 15 min/dag | I4: 15000
A5: Herber 127 CNC Rørbukker | B5: Operatør | C5: Bukkearm, hydraulik, sensorer | D5: Hydrauliklækage kan stoppe produktion | E5: Hydraulikcheck hver 3. måned | F5: Hydraulikolie hver 12. måned | G5: Let aftørring + olieafdrypning | H5: 10 min/dag | I5: 10000
A6: CoWelder – PITIG350 | B6: Operatør | C6: Brænder, dyser, køling | D6: Tilstoppet gasdyse = dårlige svejsninger | E6: Dyserensning hver uge | F6: Dyser hver 3. måned | G6: Fjerne svejsestøv | H6: 5 min/dag | I6: 8000
A7: Bodor T-Trans laserskærer/boremaskine | B7: Operatør | C7: Laserhoved, linser, føringer | D7: Linseskade stopper produktion | E7: Justering og filterskift hver. 3. måned | F7: Linser hver 12. måned | G7: Støv og metalpartikler fjernes | H7: 10 min/dag | I7: 20000
A8: Biesse Rover K Smart 1532 – CNC Skærer | B8: Operatør | C8: Spindel, vakuumbord | D8: Vakuumtab kan ødelægge emner | E8: Spindelsmøring hver måned | F8: Filter hver 6. måned | G8: Sug spåner og tør maskine | H8: 20 min/dag | I8: 12000
A9: OMMA Open Glue Spreader | B9: Operatør | C9: Limrulle, varmelegeme | D9: Tørret lim = maskinstop | E9: Ruller renses hver 7. dag | F9: Rulle hver 12. måned | G9: Afvaskning efter skift | H9: 15 min/skift | I9: 5000
A10: Spray Paint Powder Coating Line | B10: Operatør | C10: Sprøjtehoveder, filter | D10: ujævn maling | E10: Filterskift hver måned | F10: Dysser hver 6. Måned | G10: Fjern overskydene pulver | H10: 20 min/dag | I10: 15000
A11: OD120 Tube End Deburring Machine | B11: Operatør | C11: Fræsehoved, skæresystem | D11: Slid på fræsebit skaber ujævne rør | E11: Smøring hver måned | F11: Fræsebit hver 2. måned | G11: Fjern spåner | H11: 10 min/dag | I11: 4000
A12: QuickWood QT4 – Sæde slibemaskine | B12: Operatør | C12: Slibehoveder, motor | D12: Slibehoveder slides hurtigt | E12: Kontrol af slibehoved hver 3. Måned | F12: Hver måned | G12: støv fjernes | H12: 10 min/dag | I12: 6000
A13: SAGA HF-2025-0058 – Press Machine for Chair Seats | B13: Operatør | C13: Forme, hydraulik | D13: Skæv form fører til defekte sæder | E13: Formcheck hver måned | F13: Hydralikolie hver 12. måned | G13: Fjern limrester | H13: 10 min/dag | I13: 8000
A14: Evans Midwest Lay-Up Table | B14: Operatør | C14: Ruller, transportmekanisme | D14: Dårlig glideevne stopper flow | E14: Smøring hver 3. Måned | F14: Ruller efter behov | G14: Aftørring | H14: 5 min/dag | I14: 3000
A15: Rover A Smart 1632 – CNC Router | B15: Operatør | C15: Spindel, kuglespindler, vakuumbord | D15: Ujævn bevægelse | E15: Smøring af spindel og kuglespindler hver 2. måned | F15: Vakuumfilter hver 6. måned | G15: Fjern spåner, sug vakuumzoner | H15: 15 min/dag | I15: 10000
A16: Total | I16: =SUM(I4:I15) -> 116000
A21: Værktøj
A22: Navn | B22: Pris | C22: Styk
A23: Topnøglesæt | B23: 381 | C23: 2
A24: Unbrakonøgler | B24: 91 | C24: 2
A25: Skruetrækker | B25: 400 | C25: 2
A26: Hammer | B26: 103 | C26: 3
A27: Gummi hammer | B27: 50 | C27: 3
A28: Målebånd | B28: 72 | C28: 4
A29: Vinkelmåler | B29: 80 | C29: 3
A30: Fil sæt | B30: 165 | C30: 4
A31: Sandpapir | B31: 120 | C31: 4
A32: Blyant x50 | B32: 200 | C32: 1
A35: OEE (For flaskehalsen) | I35: Tilgænglighed= | J35: =B38/B36 -> 0.90625 | K35: =J35 -> 0.90625
A36: Tid til rådighed | B36: 16 | I36: Performance= | J36: =B45/B43 -> 0.96551724 | K36: =J36 -> 0.96551724
I37: Kvalitet | J37: =B46/B45 -> 0.97142857 | K37: =J37 -> 0.97142857
A38: Produktionstid | B38: 14.5 | E38: Omstilling | I38: OEE | J38: =(J35*J36*J37)*100 -> 85 | K38: %
E39: Pause
E40: Nedbrud
E41: 2 timer
A43: Mulige antal emner | B43: 435
A45: Reelt produceret | B45: 420 | E45: Ventetid Ting driller Nedsat hastighed
A46: Antal godkendte emner | B46: 408 | E46: Kasseret pga. fejl
A53: Gantt kort
A54: Produktion af 10-Højstol
F55: Daghold: | J55: Aftenhold: | N55: Pause: | Q55: Kontrol: | U55: Vedligehold: | Y55: Transport:
A56: Driftens startdato: | B56: 46002
A57: Beskrivelse af milepæl | B57: Produktion i timen | C57: Mulige antal emner pr. Dag (Medregnet tid til vedligehold) | D57: Antal lavet 1 dag i forvejen | E57: Antal til overs fra opstartsdagen | F57: 0.33333333 | G57: 0.34375 | H57: 0.35416667 | I57: 08.45 | J57: 0.375 | K57: 0.38541667 | L57: 0.39583333 | M57: 0.40625 | N57: 0.41666667 | O57: 0.42708333 | P57: 0.4375 | Q57: 0.44791667 | R57: 0.45833333 | S57: 0.46875 | T57: 0.47916667 | U57: 0.48958333 | V57: 0.5 | W57: 0.51041667 | X57: 0.52083333 | Y57: 0.53125 | Z57: 0.54166667 | AA57: 0.55208333 | AB57: 0.5625 | AC57: 0.57291667 | AD57: 0.58333333 | AE57: 0.59375 | AF57: 0.60416667 | AG57: 0.61458333 | AH57: 0.625 | AI57: 0.63541667 | AJ57: 0.64583333 | AK57: 0.65625 | AL57: 0.66666667 | AM57: 0.67708333 | AN57: 0.6875 | AO57: 0.69791667 | AP57: 0.70833333 | AQ57: 0.71875 | AR57: 0.72916667 | AS57: 0.73958333 | AT57: 0.75 | AU57: 0.76041667 | AV57: 0.77083333 | AW57: 0.78125 | AX57: 0.79166667 | AY57: 0.80208333 | AZ57: 0.8125 | BA57: 0.82291667 | BB57: 0.83333333 | BC57: 0.84375 | BD57: 0.85416667 | BE57: 0.86458333 | BF57: 0.875 | BG57: 0.88541667 | BH57: 0.89583333 | BI57: 0.90625 | BJ57: 0.91666667 | BK57: 0.92708333 | BL57: 0.9375 | BM57: 0.94791667 | BN57: 0.95833333 | BO57: 0.96875 | BP57: 0.97916667 | BQ57: 0.98958333 | BR57: 0 | BS57: Antal lavet på 1 dag efter 1 dags opstart
A58: Sæde 10-200
A59: Skære | B59: 30 stk | C59: 435 stk | D59: 435 stk | G59: 30 | K59: 30 | O59: 30 | S59: 15 | W59: 15 | Y59: 30 | AC59: 30 | AG59: 30 | AK59: 15 | AM59: 15 | AO59: 30 | AS59: 30 | AW59: 30 | BC59: 30 | BG59: 30 | BK59: 30 | BO59: 15 | BS59: =SUM(G59:BP59) -> 435
A60: Lime | B60: 40 stk | C60: 580 stk | D60: 405 stk | E60: 30 stk klar | H60: 30 | L60: 30 | P60: 30 | S60: 20 | W60: 10 | Z60: 30 | AD60: 30 | AH60: 30 | AK60: 20 | AM60: 10 | AP60: 30 | AS60: 30 | AW60: 30 | BD60: 30 | BH60: 30 | BL60: 30 | BO60: 20 | BS60: =SUM(H60:BP60) -> 440
A61: Tørre | B61: 40 stk | C61: 580 stk | D61: 475 stk | J61: 30 | O61: 30 | S61: 30 | Y61: 30 | AC61: 30 | AG61: 30 | AK61: 30 | AO61: 30 | AR61: 30 | AV61: 30 | AZ61: 10 | BC61: 20 | BG61: 30 | BK61: 30 | BO61: 30 | BS61: =SUM(J61:BO61) -> 420
A62: Presse | B62: 35 stk | C62: 507,5 stk | D62: 345 stk | E62: 60 stk klar | I62: 35 | M62: 35 | Q62: 35 | W62: 35 | AA62: 35 | AE62: 35 | AI62: 30 | AM62: 30 | AQ62: 30 | AU62: 30 | AY62: 15 | BC62: 15 | BE62: 30 | BI62: 30 | BM62: 30 | BS62: =SUM(G62:BP62) -> 450
A63: Afgrate + bore | B63: 60 stk | C63: 870 stk | D63: 315 stk | E63: 30 stk klar | K63: 30 | N63: 35 | R63: 35 | W63: 35 | AA63: 35 | AF63: 35 | AJ63: 35 | AN63: 30 | AQ63: 30 | AU63: 30 | AY63: 20 | BC63: 10 | BF63: 30 | BJ63: 30 | BN63: 30 | BS63: =SUM(I63:BP63) -> 450
A64: Kontrol
A65: Pudse | B65: 80 stk | C65: 1160 stk | D65: 285 stk | E65: 30 stk klar | L65: 30 | N65: 30 | Q65: 35 | W65: 35 | AA65: 35 | AE65: 35 | AI65: 35 | AM65: 35 | AQ65: 30 | AU65: 30 | AY65: 30 | BE65: 30 | BI65: 30 | BM65: 30 | BS65: =SUM(I65:BP65) -> 450
A66: Male + tørre | B66: 35 stk | C66: 508 stk | D66: 255 stk | E66: 30 stk klar | J66: 30 | N66: 30 | R66: 22 | W66: 8 | X66: 35 | AB66: 35 | AF66: 35 | AJ66: 27 | AM66: 8 | AN66: 35 | AR66: 35 | AV66: 30 | AZ66: 8 | BC66: 22 | BF66: 30 | BJ66: 30 | BN66: 22 | BS66: =SUM(J66:BP66) -> 442
A67: Kontrol
A68: Transport til montage | E68: 19 stk klar | O68: 30 | S68: 30 | Y68: 30 | AC68: 35 | AG68: 35 | AK68: 35 | AO68: 35 | AS68: 35 | AW68: 35 | BC68: 30 | BG68: 30 | BK68: 30 | BO68: 30 | BR68: 22 | BS68: =SUM(G68:BR68) -> 442
A69: Stel 10-100
A70: Bore + save | B70: 130 stk | C70: 1885 stk | D70: 345 stk | G70: 130 | K70: 130 | O70: 130 | S70: 65 | W70: 65 | BS70: =SUM(G70:BP70) -> 520
A71: Afgrate | B71: 360 stk | C71: 5220 stk | D71: 345 stk | K71: 130 | O71: 130 | S71: 130 | Y71: 130 | BS71: =SUM(G71:BP71) -> 520
A72: Kontrol
A73: Bukke | B73: 34 stk | C73: 493 stk | D73: 255 stk | E73: 90 stk klar | G73: 34 | K73: 34 | O73: 34 | S73: 17 | W73: 17 | Y73: 34 | AC73: 34 | AG73: 34 | AK73: 17 | AM73: 17 | AO73: 34 | AS73: 34 | AW73: 34 | BC73: 34 | BG73: 34 | BK73: 34 | BP73: 8 | BS73: =SUM(G73:BP73) -> 484
A74: Svejse | B74: 90 stk | C74: 1305 stk | D74: 255 stk | K74: 34 | O74: 34 | S74: 34 | Y74: 34 | AC74: 34 | AG74: 34 | AK74: 34 | AO74: 34 | AS74: 34 | AW74: 34 | BC74: 34 | BG74: 34 | BK74: 34 | BO74: 34 | BS74: =SUM(G74:BQ74) -> 476
A75: Kontrol
A76: Transport til montage | E76: 19 stk klar | N76: 34 | R76: 34 | X76: 34 | AB76: 34 | AF76: 34 | AJ76: 34 | AN76: 34 | AR76: 34 | AV76: 34 | AZ76: 34 | BF76: 34 | BJ76: 34 | BN76: 34 | BR76: 34
A77: Indsats i sæde 1001
A78: Dreje + skære | B78: 144 stk | C78: 2088 stk | D78: 1020 stk | G78: 144 | K78: 144 | O78: 144 | S78: 72 | W78: 72 | Y78: 144 | AC78: 144 | AG78: 144 | AK78: 72 | AM78: 72 | AO78: 144 | AS78: 144 | AW78: 144 | BC78: 72 | BS78: =SUM(F78:BQ78) -> 1656
A79: Kontrol
A80: Transport til montage | E80: 76 stk klar | L80: 144 | P80: 144 | T80: 144 | Z80: 144 | AD80: 144 | AH80: 144 | AL80: 144 | AP80: 144 | AT80: 144 | AZ80: 144 | BD80: 72 | BS80: =BS78 -> 1656
A81: Montage | BS81: Antal færdige stole:
A82: Montage | B82: 35 stk | C82: 525 stk | D82: 236 stk | E82: 19 stk klar | N82: 19 | P82: 30 | T82: 8 | W82: 22 | Z82: 30 | AD82: 34 | AH82: 34 | AL82: 8 | AM82: 26 | AP82: 34 | AT82: 34 | AX82: 26 | BC82: 8 | BD82: 34 | BH82: 31 | BL82: 30 | BP82: 22 | BS82: =SUM(G82:BR82) -> 430
A83: Kontrol

Sheet 11 Lagerstyring
B2: Artikel | C2: Årlig forbrug i antal stk. | D2: Antal gange der bliver indkøbt pr. År | E2: Antal købt per gang | F2: Antal på lager ved 100% | G2: Gennemsnitsfaktor | H2: Gennemsnitslager | I2: Stykpris | J2: Værdi af lagerbeholdningen | K2: Lageromkostninger | L2: Lageromkostninger pr. år | M2: Omokostning pr. Ordrer | N2: Antal ordrer pr. År | O2: Ordreomkostninger pr. År | P2: Total omkostninger pr. År
B3: Fod | C3: 416000 | D3: 1 | E3: =SUM(C3/D3) -> 416000 | F3: =SUM(E3) -> 416000 | G3: 2 | H3: =SUM(F3/G3) -> 208000 | I3: 1.2 | J3: =SUM(H3*I3) -> 249600 | K3: 0.2 | L3: =SUM(K3*J3) -> 49920 | M3: 6700 | N3: 1 | O3: =SUM(N3*M3) -> 6700 | P3: =SUM(O3+L3) -> 56620
B4: Pluks | C4: 416000 | D4: 1 | E4: =SUM(C4/D4) -> 416000 | F4: =SUM(E4) -> 416000 | G4: 2 | H4: =SUM(F4/G4) -> 208000 | I4: 1.2 | J4: =SUM(H4*I4) -> 249600 | K4: 0.2 | L4: =SUM(K4*J4) -> 49920 | M4: 6700 | N4: 1 | O4: =SUM(N4*M4) -> 6700 | P4: =SUM(O4+L4) -> 56620
B5: Spacer | C5: 832000 | D5: 1 | E5: =SUM(C5/D5) -> 832000 | F5: =SUM(E5) -> 832000 | G5: 2 | H5: =SUM(F5/G5) -> 416000 | I5: 1.5 | J5: =SUM(I5*H5) -> 624000 | K5: 0.2 | L5: =SUM(K5*J5) -> 124800 | M5: 9500 | N5: 1 | O5: =SUM(N5*M5) -> 9500 | P5: =SUM(O5+L5) -> 134300
B6: Skrue | C6: 416000 | D6: 1 | E6: =SUM(C6/D6) -> 416000 | F6: =SUM(E6) -> 416000 | G6: 2 | H6: =SUM(F6/G6) -> 208000 | I6: 0.5 | J6: =SUM(H6*I6) -> 104000 | K6: 0.2 | L6: =SUM(K6*J6) -> 20800 | M6: 6700 | N6: 1 | O6: =SUM(N6*M6) -> 6700 | P6: =SUM(O6+L6) -> 27500
B7: Indsats i fod | C7: =SUM(2000*4*52) -> 416000 | D7: 1 | E7: =SUM(C7/D7) -> 416000 | F7: =SUM(E7) -> 416000 | G7: 2 | H7: =SUM(F7/G7) -> 208000 | I7: 4.5 | J7: =SUM(I7*H7) -> 936000 | K7: 0.2 | L7: =SUM(K7*J7) -> 187200 | M7: 6700 | N7: 1 | O7: =SUM(N7*M7) -> 6700 | P7: =SUM(O7+L7) -> 193900
B8: Rør til stel | C8: =561600/5.4 -> 104000 | D8: 1 | E8: =SUM(C8/D8) -> 104000 | F8: =SUM(E8) -> 104000 | G8: 2 | H8: =SUM(F8/G8) -> 52000 | I8: 203.25 | J8: =SUM(I8*H8) -> 10569000 | K8: 0.2 | L8: =SUM(K8*J8) -> 2113800 | M8: 14800 | N8: 1 | O8: =SUM(N8*M8) -> 14800 | P8: =SUM(O8+L8) -> 2128600
B9: Finér til sæde | C9: 11556 | D9: 1 | E9: =SUM(C9/D9) -> 11556 | F9: =SUM(E9) -> 11556 | G9: 2 | H9: =SUM(F9/G9) -> 5778 | I9: 371.25 | J9: =SUM(I9*H9) -> 2145082.5 | K9: 0.2 | L9: =SUM(K9*J9) -> 429016.5 | M9: 14800 | N9: 1 | O9: =SUM(N9*M9) -> 14800 | P9: =SUM(O9+L9) -> 443816.5
B10: Lim | C10: 1158 | D10: 1 | E10: =SUM(C10/D10) -> 1158 | F10: =SUM(E10) -> 1158 | G10: 2 | H10: =SUM(F10/G10) -> 579 | I10: 2050 | J10: =SUM(I10*H10) -> 1186950 | K10: 0.2 | L10: =SUM(K10*J10) -> 237390 | M10: 6700 | N10: 1 | O10: =SUM(N10*M10) -> 6700 | P10: =SUM(O10+L10) -> 244090
B11: Maling | C11: =(0.1701*2000*52)/3 -> 5896.8 | D11: 1 | E11: =SUM(C11/D11) -> 5896.8 | F11: =SUM(E11) -> 5896.8 | G11: 2 | H11: =SUM(F11/G11) -> 2948.4 | I11: 494.25 | J11: =SUM(I11*H11) -> 1457246.7 | K11: 0.2 | L11: =SUM(K11*J11) -> 291449.34 | M11: 6700 | N11: 1 | O11: =SUM(N11*M11) -> 6700 | P11: =SUM(O11+L11) -> 298149.34
B12: Rør til indsats i sæde | C12: 112 | D12: 1 | E12: =SUM(C12/D12) -> 112 | F12: =SUM(E12) -> 112 | G12: 2 | H12: =SUM(F12/G12) -> 56 | I12: 431.25 | J12: =SUM(I12*H12) -> 24150 | K12: 0.2 | L12: =SUM(K12*J12) -> 4830 | M12: 6700 | N12: 1 | O12: =SUM(N12*M12) -> 6700 | P12: =SUM(O12+L12) -> 11530
B13: I Alt: | E13: =SUM(E3:E12) -> 2618722.8 | F13: =SUM(E13) -> 2618722.8 | H13: =SUM(H3:H12) -> 1309361.4 | I13: =SUM(I3:I12) -> 3558.9 | J13: =SUM(J3:J12) -> 17545629 | L13: =SUM(L3:L12) -> 3509125.8 | M13: =SUM(M3:M12) -> 86000 | O13: =SUM(O3:O12) -> 86000 | P13: =SUM(P3:P12) -> 3595125.8
A15: Fod | B15: Indkøb pr. År | C15: 1x | D15: 2x | E15: 3x | F15: 4x | G15: 5x | L15: Fod | M15: Optimal ordrestørrelse ved brug af Wilson's formel
B16: Indkøb pr- gang | C16: =C3 -> 416000 | D16: =C16/2 -> 208000 | E16: =C16/3 -> 138666.67 | F16: =C16/4 -> 104000 | G16: =C16/5 -> 83200
B17: Gennemsnintslager - stk. | C17: =H3 -> 208000 | D17: =C17/2 -> 104000 | E17: =C17/3 -> 69333.333 | F17: =C17/4 -> 52000 | G17: =C17/5 -> 41600 | M17: Optimal ordrestørrelse | N17: (2*416.000*6.700) | O17: 152402.97
B18: Gennemsnitslager - pris | C18: =J3 -> 249600 | D18: =C18/2 -> 124800 | E18: =C18/3 -> 83200 | F18: =C18/4 -> 62400 | G18: =C18/5 -> 49920 | N18: 1,20*0,20
B19: Lageromkostninger
B20: Kr. Pr. År | C20: =L3 -> 49920 | D20: =C20/2 -> 24960 | E20: =C20/3 -> 16640 | F20: =C20/4 -> 12480 | G20: =C20/5 -> 9984 | M20: Ordreomkostninger | N20: 416.000*6700 | O20: 18288.35
B21: Ordreomkostninger | N21: 152403
B22: Kr. Pr. År. | C22: =O3 -> 6700 | D22: =C22*2 -> 13400 | E22: =C22*3 -> 20100 | F22: =C22*4 -> 26800 | G22: =C22*5 -> 33500
M23: Lageromkostninger | N23: 152.403*1,20*0,20 | O23: 18288.36
B24: Omkostninger i alt - kr. | C24: =P3 -> 56620 | D24: =D20+D22 -> 38360 | E24: =E20+E22 -> 36740 | F24: =F20+F22 -> 39280 | G24: =G20+G22 -> 43484 | N24: 2
G25: I alt pr. År:
G26: =E24*3 -> 110220 | M26: Totale omkostninger | N26: 18288+18288 | O26: 36576
A28: Pluks | B28: Indkøb pr. År | C28: 1x | D28: 2x | E28: 3x | F28: 4x | G28: 5x | L28: Pluks | M28: Optimal ordrestørrelse ved brug af Wilson's formel
B29: Indkøb pr- gang | C29: =C4 -> 416000 | D29: =C29/2 -> 208000 | E29: =C29/3 -> 138666.67 | F29: =C29/4 -> 104000 | G29: =C29/5 -> 83200
B30: Gennemsnintslager - stk. | C30: =H4 -> 208000 | D30: =C30/2 -> 104000 | E30: =C30/3 -> 69333.333 | F30: =C30/4 -> 52000 | G30: =C30/5 -> 41600 | M30: Optimal ordrestørrelse | N30: (2*416.000*6.700) | O30: 152402.97
B31: Gennemsnitslager - pris | C31: =J4 -> 249600 | D31: =C31/2 -> 124800 | E31: =C31/3 -> 83200 | F31: =C31/4 -> 62400 | G31: =C31/5 -> 49920 | N31: 1,20*0,20
B32: Lageromkostninger
B33: Kr. Pr. År | C33: =L4 -> 49920 | D33: =C33/2 -> 24960 | E33: =C33/3 -> 16640 | F33: =C33/4 -> 12480 | G33: =C33/5 -> 9984 | M33: Ordreomkostninger | N33: 416.000*6700 | O33: 18288.35
B34: Ordreomkostninger | N34: 152403
B35: Kr. Pr. År. | C35: =O4 -> 6700 | D35: =C35*2 -> 13400 | E35: =C35*3 -> 20100 | F35: =C35*4 -> 26800 | G35: =C35*5 -> 33500
M36: Lageromkostninger | N36: 152.403*1,20*0,20 | O36: 18288.36
B37: Omkostninger i alt - kr. | C37: =P4 -> 56620 | D37: =D33+D35 -> 38360 | E37: =E33+E35 -> 36740 | F37: =F33+F35 -> 39280 | G37: =G33+G35 -> 43484 | N37: 2
G38: I alt pr. År:
G39: =E37*3 -> 110220 | M39: Totale omkostninger | N39: 18288+18288 | O39: 36576
A41: Spacer | B41: Indkøb pr. År | C41: 1x | D41: 2x | E41: 3x | F41: 4x | G41: 5x | L41: Spacer | M41: Optimal ordrestørrelse ved brug af Wilson's formel
B42: Indkøb pr- gang | C42: =C5 -> 832000 | D42: =C42/2 -> 416000 | E42: =C42/3 -> 277333.33 | F42: =C42/4 -> 208000 | G42: =C42/5 -> 166400
B43: Gennemsnintslager - stk. | C43: =H5 -> 416000 | D43: =C43/2 -> 208000 | E43: =C43/3 -> 138666.67 | F43: =C43/4 -> 104000 | G43: =C43/5 -> 83200 | M43: Optimal ordrestørrelse | N43: (2*832.000*9500) | O43: 229550
B44: Gennemsnitslager - pris | C44: =J5 -> 624000 | D44: =C44/2 -> 312000 | E44: =C44/3 -> 208000 | F44: =C44/4 -> 156000 | G44: =C44/5 -> 124800 | N44: 1,5*0,20
B45: Lageromkostninger
B46: Kr. Pr. År | C46: =L5 -> 124800 | D46: =C46/2 -> 62400 | E46: =C46/3 -> 41600 | F46: =C46/4 -> 31200 | G46: =C46/5 -> 24960 | M46: Ordreomkostninger | N46: 832.000*9500 | O46: 26386.2
B47: Ordreomkostninger | N47: 229550.3
B48: Kr. Pr. År. | C48: =O5 -> 9500 | D48: =C48*2 -> 19000 | E48: =C48*3 -> 28500 | F48: =C48*4 -> 38000 | G48: =C48*5 -> 47500
M49: Lageromkostninger | N49: 299.550*1,5*0,20 | O49: 44925
B50: Omkostninger i alt - kr. | C50: =C46+C48 -> 134300 | D50: =D46+D48 -> 81400 | E50: =E46+E48 -> 70100 | F50: =F46+F48 -> 69200 | G50: =G46+G48 -> 72460 | N50: 2
G51: I alt pr. År:
G52: =F50*4 -> 276800 | M52: Totale omkostninger | N52: 26.386,2+44.925 | O52: 71311.2
A54: Skrue | B54: Indkøb pr. År | C54: 1x | D54: 2x | E54: 3x | F54: 4x | G54: 5x | L54: Skrue | M54: Optimal ordrestørrelse ved brug af Wilson's formel
B55: Indkøb pr- gang | C55: =C6 -> 416000 | D55: =C55/2 -> 208000 | E55: =C55/3 -> 138666.67 | F55: =C55/4 -> 104000 | G55: =C55/5 -> 83200
B56: Gennemsnintslager - stk. | C56: =H6 -> 208000 | D56: =C56/2 -> 104000 | E56: =C56/3 -> 69333.333 | F56: =C56/4 -> 52000 | G56: =C56/5 -> 41600 | M56: Optimal ordrestørrelse | N56: (2*416.000*6.700) | O56: 236101.67
B57: Gennemsnitslager - pris | C57: =J6 -> 104000 | D57: =C57/2 -> 52000 | E57: =C57/3 -> 34666.667 | F57: =C57/4 -> 26000 | G57: =C57/5 -> 20800 | N57: 0,5*0,20
B58: Lageromkostninger
B59: Kr. Pr. År | C59: =L6 -> 20800 | D59: =C59/2 -> 10400 | E59: =C59/3 -> 6933.3333 | F59: =C59/4 -> 5200 | G59: =C59/5 -> 4160 | M59: Ordreomkostninger | N59: 416.000*6.700 | O59: 11805.06
B60: Ordreomkostninger | N60: 236102
B61: Kr. Pr. År. | C61: =M6 -> 6700 | D61: =C61*2 -> 13400 | E61: =C61*3 -> 20100 | F61: =C61*4 -> 26800 | G61: =C61*5 -> 33500
M62: Lageromkostninger | N62: 236.102*0,5*0,20 | O62: 11805
B63: Omkostninger i alt - kr. | C63: =C59+C61 -> 27500 | D63: =D59+D61 -> 23800 | E63: =E59+E61 -> 27033.333 | F63: =F59+F61 -> 32000 | G63: =G59+G61 -> 37660 | N63: 2
G64: I alt pr. År:
G65: =D63*2 -> 47600 | M65: Totale omkostninger | N65: 11.805+11.805 | O65: 23610
A67: Indsats i fod | B67: Indkøb pr. År | C67: 1x | D67: 2x | E67: 3x | F67: 4x | G67: 5x | H67: 6x | L67: Indsats i fod | M67: Optimal ordrestørrelse ved brug af Wilson's formel
B68: Indkøb pr- gang | C68: =C7 -> 416000 | D68: =C68/2 -> 208000 | E68: =C68/3 -> 138666.67 | F68: =C68/4 -> 104000 | G68: =C68/5 -> 83200 | H68: =C68/6 -> 69333.333
B69: Gennemsnintslager - stk. | C69: =H7 -> 208000 | D69: =C69/2 -> 104000 | E69: =C69/3 -> 69333.333 | F69: =C69/4 -> 52000 | G69: =C69/5 -> 41600 | H69: =C69/6 -> 34666.667 | M69: Optimal ordrestørrelse | N69: (2*416.000*6700) | O69: 78701
B70: Gennemsnitslager - pris | C70: =J7 -> 936000 | D70: =C70/2 -> 468000 | E70: =C70/3 -> 312000 | F70: =C70/4 -> 234000 | G70: =C70/5 -> 187200 | H70: =C70/6 -> 156000 | N70: 4,5*0,20
B71: Lageromkostninger
B72: Kr. Pr. År | C72: =L7 -> 187200 | D72: =C72/2 -> 93600 | E72: =C72/3 -> 62400 | F72: =C72/4 -> 46800 | G72: =C72/5 -> 37440 | H72: =C72/6 -> 31200 | M72: Ordreomkostninger | N72: 416.000*6.700 | O72: 35505.28
B73: Ordreomkostninger | N73: 78501
B74: Kr. Pr. År. | C74: =O7 -> 6700 | D74: =C74*2 -> 13400 | E74: =C74*3 -> 20100 | F74: =C74*4 -> 26800 | G74: =C74*5 -> 33500 | H74: =C74*6 -> 40200
M75: Lageromkostninger | N75: 78.701*4,5*0,20 | O75: 35415.45
B76: Omkostninger i alt - kr. | C76: =C72+C74 -> 193900 | D76: =D72+D74 -> 107000 | E76: =E72+E74 -> 82500 | F76: =F72+F74 -> 73600 | G76: =G72+G74 -> 70940 | H76: =H72+H74 -> 71400 | N76: 2
H77: I alt pr. År:
H78: =G76*5 -> 354700 | M78: Totale omkostninger | N78: 35.505+35.415,45 | O78: 70920.45
A80: Rør til stel | B80: Indkøb pr. År | C80: 1x | D80: 2x | E80: 3x | F80: 4x | G80: 5x | H80: 6x | I80: 7x | J80: 8x | K80: 8x | L80: Rør til stel | M80: Optimal ordrestørrelse ved brug af Wilson's formel
B81: Indkøb pr- gang | C81: =C8 -> 104000 | D81: =C81/2 -> 52000 | E81: =C81/3 -> 34666.667 | F81: =C81/4 -> 26000 | G81: =C81/5 -> 20800 | H81: =C81/6 -> 17333.333 | I81: =C81/7 -> 14857.143 | J81: =C81/8 -> 13000 | K81: =D81/9 -> 5777.7778
B82: Gennemsnintslager - stk. | C82: =H8 -> 52000 | D82: =C82/2 -> 26000 | E82: =C82/3 -> 17333.333 | F82: =C82/4 -> 13000 | G82: =C82/5 -> 10400 | H82: =C82/6 -> 8666.6667 | I82: =C82/7 -> 7428.5714 | J82: =C82/8 -> 6500 | K82: =D82/9 -> 2888.8889 | M82: Optimal ordrestørrelse | N82: (2*104.000*14.800) | O82: 8702.26
B83: Gennemsnitslager - pris | C83: =J8 -> 10569000 | D83: =C83/2 -> 5284500 | E83: =C83/3 -> 3523000 | F83: =C83/4 -> 2642250 | G83: =C83/5 -> 2113800 | H83: =C83/6 -> 1761500 | I83: =C83/7 -> 1509857.1 | J83: =C83/8 -> 1321125 | K83: =D83/9 -> 587166.67 | N83: 203,25*0,20
B84: Lageromkostninger
B85: Kr. Pr. År | C85: =L8 -> 2113800 | D85: =C85/2 -> 1056900 | E85: =C85/3 -> 704600 | F85: =C85/4 -> 528450 | G85: =C85/5 -> 422760 | H85: =C85/6 -> 352300 | I85: =C85/7 -> 301971.43 | J85: =C85/8 -> 264225 | K85: =D85/9 -> 117433.33 | M85: Ordreomkostninger | N85: 104.000*14.800 | O85: 176878.87
B86: Ordreomkostninger | N86: 8702
B87: Kr. Pr. År. | C87: =O8 -> 14800 | D87: =C87*2 -> 29600 | E87: =C87*3 -> 44400 | F87: =C87*4 -> 59200 | G87: =C87*5 -> 74000 | H87: =C87*6 -> 88800 | I87: =C87*7 -> 103600 | J87: =C87*8 -> 118400 | K87: =D87*9 -> 266400
M88: Lageromkostninger | N88: 8.702*203,25*0,20 | O88: 176868.15
B89: Omkostninger i alt - kr. | C89: =C85+C87 -> 2128600 | D89: =D87+D85 -> 1086500 | E89: =E87+E85 -> 749000 | F89: =F85+F87 -> 587650 | G89: =G85+G87 -> 496760 | H89: =H87+H85 -> 441100 | I89: =I85+I87 -> 405571.43 | J89: =J85+J87 -> 382625 | K89: =K85+K87 -> 383833.33 | N89: 2
K90: I alt pr. År:
K91: =J89*8 -> 3061000 | M91: Totale omkostninger | N91: 176.879+176.868 | O91: 353747.15
A93: Finér til sæde | B93: Indkøb pr. År | C93: 1x | D93: 2x | E93: 3x | F93: 4x | G93: 5x | H93: 6x | L93: Finér til sæde | M93: Optimal ordrestørrelse ved brug af Wilson's formel
B94: Indkøb pr- gang | C94: =C9 -> 11556 | D94: =C94/2 -> 5778 | E94: =C94/3 -> 3852 | F94: =C94/4 -> 2889 | G94: =C94/5 -> 2311.2 | H94: =C94/6 -> 1926
B95: Gennemsnintslager - stk. | C95: =H9 -> 5778 | D95: =C95/2 -> 2889 | E95: =C95/3 -> 1926 | F95: =C95/4 -> 1444.5 | G95: =C95/5 -> 1155.6 | H95: =C95/6 -> 963 | M95: Optimal ordrestørrelse | N95: (2*11.556*14.800) | O95: 2146.35
B96: Gennemsnitslager - pris | C96: =J9 -> 2145082.5 | D96: =C96/2 -> 1072541.2 | E96: =C96/3 -> 715027.5 | F96: =C96/4 -> 536270.62 | G96: =C96/5 -> 429016.5 | H96: =C96/6 -> 357513.75 | N96: 371,25*0,20
B97: Lageromkostninger
B98: Kr. Pr. År | C98: =L9 -> 429016.5 | D98: =C98/2 -> 214508.25 | E98: =C98/3 -> 143005.5 | F98: =C98/4 -> 107254.12 | G98: =C98/5 -> 85803.3 | H98: =C98/6 -> 71502.75 | M98: Ordreomkostninger | N98: 11.556*14.800 | O98: 79696.55
B99: Ordreomkostninger | N99: 2146
B100: Kr. Pr. År. | C100: =O9 -> 14800 | D100: =C100*2 -> 29600 | E100: =C100*3 -> 44400 | F100: =C100*4 -> 59200 | G100: =C100*5 -> 74000 | H100: =C100*6 -> 88800
M101: Lageromkostninger | N101: 2.146*371,25*0,20 | O101: 79670.25
B102: Omkostninger i alt - kr. | C102: =C98+C100 -> 443816.5 | D102: =D98+D100 -> 244108.25 | E102: =E98+E100 -> 187405.5 | F102: =F98+F100 -> 166454.12 | G102: =G98+G100 -> 159803.3 | H102: =H100+H98 -> 160302.75 | N102: 2
H103: I alt pr. År:
H104: =G102*5 -> 799016.5 | M104: Totale omkostninger | N104: 79.697+79.670 | O104: 159367.25
A106: Lim | B106: Indkøb pr. År | C106: 1x | D106: 2x | E106: 3x | F106: 4x | G106: 5x | H106: 6x | I106: 7x | L106: Lim | M106: Optimal ordrestørrelse ved brug af Wilson's formel
B107: Indkøb pr- gang | C107: =C10 -> 1158 | D107: =C107/2 -> 579 | E107: =C107/3 -> 386 | F107: =C107/4 -> 289.5 | G107: =C107/5 -> 231.6 | H107: =C107/6 -> 193 | I107: =C107/7 -> 165.42857
B108: Gennemsnintslager - stk. | C108: =H10 -> 579 | D108: =C108/2 -> 289.5 | E108: =C108/3 -> 193 | F108: =C108/4 -> 144.75 | G108: =C108/5 -> 115.8 | H108: =C108/6 -> 96.5 | I108: =C108/7 -> 82.714286 | M108: Optimal ordrestørrelse | N108: (2*1.158*6.700) | O108: 194.54
B109: Gennemsnitslager - pris | C109: =J10 -> 1186950 | D109: =C109/2 -> 593475 | E109: =C109/3 -> 395650 | F109: =C109/4 -> 296737.5 | G109: =C109/5 -> 237390 | H109: =C109/6 -> 197825 | I109: =C109/7 -> 169564.29 | N109: 2.050*0,20
...

Sheet 12 MRP
C5: Component ID | D5: Description | E5: Type | F5: Total Qty | G5: Unit | H5: Matrialer
C6: 10- Højstol | D6: Stol assembly | E6: BOM | H6: N/A
C7: 10-200 | D7: Sæde | E7: Item | F7: 1 | G7: EA | H7: Plywood
C8: 810 | D8: Lim | E8: Item | F8: 167 | G8: ml | H8: N/A
C9: 820 | D9: Sort maling RAL9005 | E9: Item | F9: 170.7 | G9: ml | H9: N/A
C10: 1003 | D10: Spacer | E10: Item | F10: 8 | G10: EA | H10: POM
C11: 1001 | D11: Indsats i sæde | E11: Item | F11: 4 | G11: EA | H11: AISI 316 Stainless Steel Bar(SS)
C12: 1002 | D12: Skrue | E12: Item | F12: 4 | G12: EA | H12: N/A
C13: 10-100 | D13: Stel | E13: BOM | H13: N/A
C14: 10-101 | D14: Forben | E14: Item | F14: 1 | G14: EA | H14: AISI 1045 Steel, cold drawn
C15: 10-102 | D15: Tværrør ben | E15: Item | F15: 2 | G15: EA | H15: AISI 1045 Steel, cold drawn
C16: 10-103 | D16: Bagben | E16: Item | F16: 1 | G16: EA | H16: AISI 1045 Steel, cold drawn
C17: 10-104 | D17: Tværrør mellem | E17: Item | F17: 1 | G17: EA | H17: AISI 1045 Steel, cold drawn
C18: 10-105 | D18: Tværrør oven | E18: Item | F18: 2 | G18: EA | H18: AISI 1045 Steel, cold drawn
C19: 10-300 | D19: Fod | E19: BOM | H19: N/A
C20: 1005 | D20: Pluks | E20: Item | F20: 4 | G20: EA | H20: PP
C21: 1004 | D21: Fod | E21: Item | F21: 4 | G21: EA | H21: PP
C22: 1006 | D22: Indsats til fod | E22: Item | F22: 4 | G22: EA | H22: AISI 316 Annealed Stainless Steel Bar (SS)

Sheet 13 Etableringsbudget
D1: Etableringsbudget
A2: Titel | D2: Projekt fabrik | O2: grøn=rigtige tal
A3: Kontrolleret | D3: initialer | G3: Revisionsnr. | H3: nummer | O3: Gul=estimat
A4: Forfatter | D4: initialer | G4: Ændret den | H4: dato
A5: Omkostninger
B6: Stykpris | C6: Antal | D6: DKK | E6: Kilder
A7: Lokaler og infrastruktur | D7: =SUM(D8:D13) -> 760549
A8: Husleje (1 måned) | B8: 40187 | C8: 1 | D8: =B8*C8 -> 40187 | E8: https://www.edc.dk/erhverv/erhvervslejemaal/lager-produktion/6705-esbjerg-oe/spangsbjerg-moellevej-100/670114509/
A9: Depositum | B9: 120562 | C9: 1 | D9: =B9*C9 -> 120562
A10: Istandsættelse | B10: 300000 | C10: 1 | D10: =B10*C10 -> 300000
A11: Tilladelser | B11: 50000 | C11: 1 | D11: =B11*C11 -> 50000
A12: Opsætninger af forsyninger | B12: 100000 | C12: 1 | D12: 100000
A13: Varevogn | B13: 149800 | C13: 1 | D13: =B13*C13 -> 149800 | E13: https://www.bilbasen.dk/brugt/varebil-ekskl-moms/ford/transit-connect/15-ecoblue-trend-aut-lang/6615504
A15: Produktionsudstyr | D15: =SUM(D16:D19) -> 6028877
A16: Maskiner | D16: ='7 Maskinliste & fremstil.valg'!O19 -> 5498416
A17: Værktøj | D17: ='Budget lister'!E58 -> 5861
A18: Installlation af maskiner | D18: ='Budget lister'!E18 -> 440000 | E18: Har bare lavet et skøn ud fra maskine prisen
A19: Gaffel trucks | B19: 84600 | C19: 2 | D19: =SUM(B19) -> 84600 | E19: https://www.dba.dk/recommerce/forsale/item/10511603 | K19: https://www.dba.dk/recommerce/forsale/item/12816048
A20: Løn | D20: =D21 -> 1235000
A21: Løn pr. måned | B21: ='3 Organisation & arbejdsopg.'!J47 -> 1235000 | C21: 1 | D21: =B21*C21 -> 1235000
A26: Sikkerhedsudstyr og tøj | D26: =SUM(D27:D30) -> 49025
A27: Sikkerhedssko | B27: 499 | C27: 25 | D27: =B27*C27 -> 12475 | E27: https://billig-arbejdstoj.dk/Sanita-S-Feel-Prenit-sikkerhedssko-S1P-Black%2Fwhite/135267.html
A28: Arbejdstøj | B28: ='Budget lister'!N9 -> 335 | C28: 100 | D28: =B28*C28 -> 33500 | E28: Links i ark "budget lister"
A29: Arbejdshandsker | B29: 29 | C29: 50 | D29: =B29*C29 -> 1450 | E29: https://billig-arbejdstoj.dk/OX-ON-Cut-D-Advanced-9903-skaerehandsker-Graa%2FSort/162176.html
A30: Høreværn | B30: 160 | C30: 10 | D30: =B30*C30 -> 1600 | E30: https://www.silvan.dk/produkt/vecta-hoerevaern-m-justerbar-boejle-sort-2880-2073920
A33: Kontorinventar | D33: =SUM(D34:D36) -> 126006.75
A34: IT hardware | B34: ='Budget lister'!E42 -> 36572.25 | C34: 3 | D34: =B34*C34 -> 109716.75
A35: Software | B35: ='Budget lister'!E32 -> 630 | C35: 3 | D35: =B35*C35 -> 1890
A36: Møbler | B36: ='Budget lister'!E25 -> 4800 | C36: 3 | D36: =B36*C36 -> 14400
A39: Vareindkøb | D39: =SUM(D40:D41) -> 931629.39
A40: halvfabrikata og materialer | B40: ='11 Lagerstyring'!O145 -> 692635.74 | C40: 1 | D40: =B40 -> 692635.74
A41: Komponenter | B41: ='11 Lagerstyring'!O147 -> 238993.65 | C41: 1 | D41: =B41*C41 -> 238993.65
A43: Rådgivere og forsikringer | D43: =SUM(D44:D46) -> 124854.16
A44: Advokoat | B44: 7000 | C44: 1 | D44: =SUM(B44*C44) -> 7000 | E44: https://www.hulgaardadvokater.dk/vores-specialer/selskaber-og-fonde/start-af-virksomhed/
A45: Revisor | B45: 5000 | C45: 1 | D45: =SUM(B45*C45) -> 5000 | E45: https://finara.dk/revisor/revisor-priser-i-2025-hvad-er-rimeligt/
A46: Forsikringer | B46: ='Budget lister'!E112 -> 112854.16 | D46: =B46 -> 112854.16 | E46: Estemater baseret på industristandarder
A47: Div | D47: =D48 -> 30000
A48: Reception ved åbning | B48: 30000 | C48: 1 | D48: =SUM(B48*C48) -> 30000
A49: Total | D49: =SUM(D47+D43+D39+D33+D26+D20+D15+D7) -> 9285941.3

Sheet Budget lister
B4: Maskine opsætting pris | G4: Test af maskiner (teknikker) | M4: Arbejdstøj | AA4: Råvarer og materiale
B5: Nummer | C5: Navn | E5: Pris | G5: Nummer | H5: Navn | I5: Pris/år | J5: Antal | K5: Estimeret pris pr måned | M5: Navn | N5: Pris | P5: https://billig-arbejdstoj.dk/Sanita-S-Feel-Prenit-sikkerhedssko-S1P-Black%2Fwhite/135267.html | Z5: Nummer | AA5: Navn | AB5: Stykpris | AC5: Antal | AD5: Pris pr uge
B6: 1 | C6: CNC Drejebænk | E6: 40000 | G6: 1 | H6: CNC Drejebænk | I6: 10000 | J6: 3 | K6: =I6/J6 -> 3333.3333 | M6: bukser | N6: 200 | P6: https://billig-arbejdstoj.dk/Engel-Enterprise-arbejdsbukser-Graa%2FSort/2620.html | Z6: 1 | AA6: Stålrør til stel
B7: 2 | C7: Spray paint | E7: 160000 | G7: 2 | H7: Spray paint | I7: 12000 | J7: 4 | K7: =I7/J7 -> 3000 | M7: T-shirt | N7: 135 | P7: https://www.spreadshirt.dk/design-selv?productType=812&productTypeCategory=CG01 | Z7: 2 | AA7: stål til indsats til sæde | AC7: 8000
B8: 3 | C8: Rør afgrater | E8: 5000 | G8: 3 | H8: Rør afgrater | I8: 4500 | J8: 3 | K8: =I8/J8 -> 1500 | P8: https://billig-arbejdstoj.dk/OX-ON-Cut-D-Advanced-9903-skaerehandsker-Graa%2FSort/162176.html | Z8: 3
B9: 4 | C9: CNC rør bøjer | E9: 35000 | G9: 4 | H9: CNC rør bøjer | I9: 5000 | J9: 4 | K9: =I9/J9 -> 1250 | M9: Total | N9: =SUM(N6:N8) -> 335 | Z9: 4
B10: 5 | C10: svejser | E10: 25000 | G10: 5 | H10: svejser | I10: 3500 | J10: 4 | K10: =I10/J10 -> 875 | Z10: 5
B11: 6 | C11: bodor T-Trans | E11: 35000 | G11: 6 | H11: bodor T-Trans | I11: 7000 | J11: 4 | K11: =I11/J11 -> 1750
B12: 7 | C12: CNC skærre Biesse | E12: 30000 | G12: 7 | H12: CNC skærre Biesse | I12: 8000 | J12: 4 | K12: =I12/J12 -> 2000 | M12: omsætning om året
B13: 8 | C13: OMMA OPEN | E13: 25000 | G13: 8 | H13: OMMA OPEN | I13: 25000 | J13: 12 | K13: =I13/J13 -> 2083.3333 | M13: Pris pr. Stol | N13: 800 | AS13: Værktøj
B14: 9 | C14: Rover K smart 1632 | E14: 30000 | G14: 9 | H14: Rover K smart 1632 | I14: 45000 | J14: 6 | K14: =I14/J14 -> 7500 | M14: Antal stole produceret pr. Uge | N14: 2000 | AS14: Navn
B15: 10 | C15: sæde sliber | E15: 20000 | G15: 10 | H15: Sæde sliber | I15: 20000 | J15: 4 | K15: =I15/J15 -> 5000 | M15: Resultat | N15: =((2000*4.333)*800)*12 -> 83193600 | AS15: Hammer
B16: 11 | C16: Støbe sæde | E16: 25000 | G16: 11 | H16: Støbe sæde
B17: 12 | C17: Lay up table | E17: 10000 | G17: 12 | H17: Lay up table
D18: total | E18: =SUM(E6:E17) -> 440000 | J18: Total | K18: =SUM(K6:K15) -> 28291.667 | M18: Kalkulationsrentefod, i
M19: rf (risikofri rente) | N19: rp(risikopræmie) | O19: Forventet inflation | P19: resultat
M20: 0.02 | N20: 0.04 | O20: 0.04 | P20: =M20+N20+O20 -> 0.1
B21: Møbler
B22: Navn | C22: Pris | D22: Antal | E22: Total | F22: Links
B23: Bord | C23: 1000 | D23: 3 | E23: =C23*D23 -> 3000 | F23: https://nimara.dk/products/damian-haeve-og-saenkebord-120x60-cm-i-sort?gad_source
B24: Stol | C24: 600 | D24: 3 | E24: =C24*D24 -> 1800 | F24: https://webdanes.dk/shop/paracon-mesh-gaming-141027p.html
B25: Total | C25: =C23+C24 -> 1600 | D25: 3 | E25: =E23+E24 -> 4800
B28: IT Software
B29: Navn | C29: Pris | D29: Antal | E29: Total | F29: Links
B30: Styresystem | C30: =150*0.75 -> 112.5 | D30: 3 | E30: =C30*D30 -> 337.5 | F30: https://www.productkeys.dk/produkt/windows-11-home-retail
B31: office pakke | C31: =130*0.75 -> 97.5 | D31: 3 | E31: =C31*D31 -> 292.5 | F31: https://www.productkeys.dk/produkt/microsoft-office-2024-standard-pc
B32: Total: | C32: =SUM(C30:C31) -> 210 | E32: =SUM(E30:E31) -> 630
B35: IT Hardware
B36: Navn | C36: Pris | D36: Antal | E36: Total | F36: Links
B37: Computer | C37: 10000 | D37: 3 | E37: =C37*D37 -> 30000 | F37: https://www.dell.com/da-dk/shop/cty/pdp/spd/dell-pro-max-fct2250-desktop
B38: Skærm | C38: =(890*0.75)*2 -> 1335 | D38: 3 | E38: =C38*D38 -> 4005 | F38: https://www.proshop.dk/Skaerm/27-Dell-Pro-E2725HM-1920x1080-FHD-100Hz-IPS
B39: Tastertur | C39: =580*0.75 -> 435 | D39: 3 | E39: =C39*D39 -> 1305 | F39: https://www.proshop.dk/Tastatur/Logitech-MX-Keys-S-Graphite-ND
B40: Mus | C40: =250*0.75 -> 187.5 | D40: 3 | E40: =C40*D40 -> 562.5 | F40: https://www.proshop.dk/Mus/Logitech-M705-Marathon-Mouse-Mus-Laser-6-knapper-Sort
B41: Høretelefoner | C41: =311*0.75 -> 233.25 | D41: 3 | E41: =C41*D41 -> 699.75 | F41: https://www.proshop.dk/Hovedtelefonerheadset2/Jabra-Evolve-20SE-MS-Stereo
B42: Total: | C42: =C37+C38+C39+C40+C41 -> 12190.75 | E42: =SUM(E37:E41) -> 36572.25
B45: Værktøj og div.
B46: Navn | C46: Pris | D46: Antal | E46: Total | F46: Links
B47: Gummi hammer | C47: 40 | D47: 5 | E47: =D47*C47 -> 200 | F47: https://www.jemogfix.dk/gummihammer-500-g/3122/9020664/
B48: Skruemaskine | C48: 348 | D48: 5 | E48: =D48*C48 -> 1740 | F48: https://www.jemogfix.dk/falke-slagskruemaskine-akku-kulfri-18-v/3101/9059149/
B49: Topnøglesæt | C49: 381 | D49: 2 | E49: =D49*C49 -> 762
B50: Unbrakonøgler | C50: 91 | D50: 2 | E50: =D50*C50 -> 182
B51: Hammer | C51: 103 | D51: 3 | E51: =D51*C51 -> 309
B52: Blyant x50 | C52: 200 | D52: 1 | E52: =D52*C52 -> 200
B53: Vinkelmåler | C53: 80 | D53: 3 | E53: =D53*C53 -> 240
B54: Fil sæt | C54: 165 | D54: 4 | E54: =D54*C54 -> 660
B55: Sandpapir | C55: 120 | D55: 4 | E55: =D55*C55 -> 480
B56: Målebånd | C56: 72 | D56: 4 | E56: =D56*C56 -> 288
B57: Skruetrækker | C57: 400 | D57: 2 | E57: =D57*C57 -> 800
B58: Total | E58: =SUM(E47:E57) -> 5861
B61: Komponenter/mnd.
B62: Enhed | C62: Materiale | D62: Pris pr. stk. | E62: Pris pr. enhed | F62: Antal | G62: Total
B63: Split til fod | C63: aisi 1020 steel | D63: 4.5 | E63: =4*D63 -> 18 | F63: 32000 | G63: =F63*D63 -> 144000
B64: Fod | C64: PP | D64: 1.2 | E64: =D64*4 -> 4.8 | F64: 32000 | G64: =F64*D64 -> 38400
B65: Plug til fod | C65: PP | D65: 1.2 | E65: =D65*4 -> 4.8 | F65: 32000 | G65: =F65*D65 -> 38400
B66: Spacer | C66: POM | D66: 1.2 | E66: =D66*8 -> 9.6 | F66: 64000 | G66: =D66*F66 -> 76800
B67: Skrue | C67: Metal | D67: 5 | E67: =D67*4 -> 20 | F67: 32000 | G67: =F67*D67 -> 160000
B68: Total | E68: =SUM(E63:E67) -> 57.2 | G68: =SUM(G63:G67) -> 457600
B71: Afskrivninger
B72: Maskiner | C72: Indkøbs pris | D72: Levetid/år | E72: Afskrivning pr år
B73: CNC Drejebænk | C73: 400000 | D73: 30 | E73: =C73/D73 -> 13333.333
B74: Rør afgrater | C74: 90000 | D74: 20 | E74: =C74/D74 -> 4500
B75: CNC rør bukker | C75: 250000 | D75: 20 | E75: =C75/D75 -> 12500
B76: svejser | C76: 600000 | D76: 12 | E76: =C76/D76 -> 50000
B77: bodor T-Trans | C77: 700000 | D77: 25 | E77: =C77/D77 -> 28000
B78: CNC skærre Biesse | C78: 340000 | D78: 15 | E78: =C78/D78 -> 22666.667
B79: OMMA OPEN | C79: 370000 | D79: 10 | E79: =C79/D79 -> 37000
B80: Rover K smart 1632 | C80: 600000 | D80: 12 | E80: =C80/D80 -> 50000
B81: sæde sliber | C81: 224115 | D81: 10 | E81: =C81/D81 -> 22411.5
B82: Spray paint | C82: 1615655 | D82: 15 | E82: =C82/D82 -> 107710.33
B83: Total | C83: =SUM(C73:C82) -> 5189770 | E83: =SUM(E73:E82) -> 348121.83
B91: Varme pr. År
B92: Lokale m2 | C92: Pris pr. M2 | D92: I alt
B93: 1929 | C93: 70 | D93: =C93*B93 -> 135030
B96: Vand pr. År
B97: Medarbejdere | C97: Vand pr. Medarbejder m3 | D97: Pris pr. m3 | E97: I alt
B98: 42 | C98: 20 | D98: 60 | E98: =(B98*C98)*D98 -> 50400
B101: Forsyning pr. År
B102: Varme | C102: Vand | D102: I alt
B103: =D93 -> 135030 | C103: =E98 -> 50400 | D103: =C103+B103 -> 185430
B106: Forsikringer pr. År
B107: Lokale | C107: m2 | D107: pris pr. M2 | E107: I alt
C108: 1929 | D108: 30 | E108: =C108*D108 -> 57870
B110: Maskiner | C110: Maskiner anskaffelsespris | D110: Procent af anskaffelsessum
C111: ='7 Maskinliste & fremstil.valg'!O19 -> 5498416 | D111: 0.01 | E111: =C111*D111 -> 54984.16
B112: I alt | E112: =E108+E111 -> 112854.16
B115: Rengøring
B116: Timer pr. Gang | C116: 2
B117: Hyppighed pr. Måned | C117: 9
B118: Pris pr. Time | C118: 300
B119: Pris pr. År | C119: =((C116*C118)*C117)*12 -> 64800

Sheet 14 Driftbudget
A3: Driftsbudget
A4: Titel | B4: Driftsbudget – Projekt masseproduktion (Case 3)
A5: Kontrolleret | B5: SBV,SRU,JFN,CVG,SLN | F5: Oprettet | G5: 45964 | I5: Revisionsnr. | J5: 1
A6: Forfatter | B6: Gruppe 3 | F6: Ansvarlig | G6: Gruppe 3 | I6: Ændret den | J6: 46001
B7: 2026 | C7: 2027 | D7: 2028 | E7: 2029 | F7: 2030 | G7: 2032 | H7: 2033 | I7: 2034 | J7: 2035 | K7: 2036 | L7: 2037 | M7: 2038
A8: Nettoomsætning | B8: ='Budget lister'!N15 -> 83193600 | C8: =B8*1.04 -> 86521344 | D8: =C8*1.04 -> 89982198 | E8: =D8*1.04 -> 93581486 | F8: =E8*1.04 -> 97324745 | G8: =F8*1.04 -> 1.0121773e+08 | H8: =G8*1.04 -> 1.0526644e+08 | I8: =H8*1.04 -> 1.094771e+08 | J8: =I8*1.04 -> 1.1385619e+08 | ... M8: =L8*1.04 -> 1.2807272e+08
A9: Løn | B9: ='3 Organisation & arbejdsopg.'!J47*12 -> 14820000 | C9: =B9*1.04 -> 15412800 | D9: =C9*1.04 -> 16029312 | E9: =D9*1.04 -> 16670484 | F9: =E9*1.04 -> 17337304 | G9: =F9*1.04 -> 18030796 | H9: =G9*1.04 -> 18752028 | I9: =H9*1.04 -> 19502109 | J9: =I9*1.04 -> 20282193 | ... M9: =L9*1.04 -> 22814709
A10: komponenter | B10: ='11 Lagerstyring'!O151 -> 899540 | C10: =B10*1.04 -> 935521.6 | D10: =C10*1.04 -> 972942.46 | E10: =D10*1.04 -> 1011860.2 | F10: =E10*1.04 -> 1052334.6 | G10: =F10*1.04 -> 1094428 | H10: =G10*1.04 -> 1138205.1 | I10: =H10*1.04 -> 1183733.3 | J10: =I10*1.04 -> 1231082.6 | ... M10: =L10*1.04 -> 1384800.5
A11: Materialer | B11: ='11 Lagerstyring'!O149 -> 4969885.8 | C11: =B11*1.04 -> 5168681.3 | D11: =C11*1.04 -> 5375428.5 | E11: =D11*1.04 -> 5590445.7 | F11: =E11*1.04 -> 5814063.5 | G11: =F11*1.04 -> 6046626 | H11: =G11*1.04 -> 6288491.1 | I11: =H11*1.04 -> 6540030.7 | J11: =I11*1.04 -> 6801631.9 | ... M11: =L11*1.04 -> 7650910.9
A12: Tændt produktion (el) | B12: ='5 Forsyningsstrategi'!A40 -> 560688.5 | C12: =B12*1.04 -> 583116.04 | D12: =C12*1.04 -> 606440.68 | E12: =D12*1.04 -> 630698.31 | F12: =E12*1.04 -> 655926.24 | G12: =F12*1.04 -> 682163.29 | H12: =G12*1.04 -> 709449.82 | I12: =H12*1.04 -> 737827.82 | J12: =I12*1.04 -> 767340.93 | ... M12: =L12*1.04 -> 863154.19
A13: Variabler i alt | B13: =B9+B10+B11+B12 -> 21250114 | C13: =B13*1.04 -> 22100119 | D13: =C13*1.04 -> 22984124 | E13: =D13*1.04 -> 23903489 | F13: =E13*1.04 -> 24859628 | G13: =F13*1.04 -> 25854013 | H13: =G13*1.04 -> 26888174 | I13: =H13*1.04 -> 27963701 | J13: =I13*1.04 -> 29082249 | ... M13: =L13*1.04 -> 32713575
A14: Dækningsbidrag | B14: =B8-B13 -> 61943486 | C14: =C8-C13 -> 64421225 | D14: =D8-D13 -> 66998074 | E14: =E8-E13 -> 69677997 | F14: =F8-F13 -> 72465117 | G14: =G8-G13 -> 75363722 | H14: =H8-H13 -> 78378270 | I14: =I8-I13 -> 81513401 | ... M14: =M8-M13 -> 95359150
A15: Tekniker | B15: ='Budget lister'!K18*12 -> 339500 | C15: =B15*1.04 -> 353080 | D15: =C15*1.04 -> 367203.2 | E15: =D15*1.04 -> 381891.33 | F15: =E15*1.04 -> 397166.98 | G15: =F15*1.04 -> 413053.66 | H15: =G15*1.04 -> 429575.81 | I15: =H15*1.04 -> 446758.84 | J15: =I15*1.04 -> 464629.19 | ... M15: =L15*1.04 -> 522644.65
A16: Vedligeholdelse | B16: ='10 Prod.plan&vedligehold'!I16 -> 116000 | C16: =B16*1.04 -> 120640 | D16: =C16*1.04 -> 125465.6 | E16: =D16*1.04 -> 130484.22 | F16: =E16*1.04 -> 135703.59 | G16: =F16*1.04 -> 141131.74 | H16: =G16*1.04 -> 146777.01 | I16: =H16*1.04 -> 152648.09 | J16: =I16*1.04 -> 158754.01 | ... M16: =L16*1.04 -> 178576.67
A17: Forsyninger (vand og varme) | B17: ='Budget lister'!D103 -> 185430 | C17: =B17*1.04 -> 192847.2 | D17: =C17*1.04 -> 200561.09 | E17: =D17*1.04 -> 208583.53 | F17: =E17*1.04 -> 216926.87 | G17: =F17*1.04 -> 225603.95 | H17: =G17*1.04 -> 234628.11 | I17: =H17*1.04 -> 244013.23 | J17: =I17*1.04 -> 253773.76 | ... M17: =L17*1.04 -> 285460.97
A18: Forsikringer | B18: ='Budget lister'!E112 -> 112854.16 | C18: =B18*1.04 -> 117368.33 | D18: =C18*1.04 -> 122063.06 | E18: =D18*1.04 -> 126945.58 | F18: =E18*1.04 -> 132023.41 | G18: =F18*1.04 -> 137304.34 | H18: =G18*1.04 -> 142796.51 | I18: =H18*1.04 -> 148508.38 | J18: =I18*1.04 -> 154448.71 | ... M18: =L18*1.04 -> 173733.79
A19: Rengøring af personale faciliteter | B19: ='Budget lister'!C119 -> 64800 | C19: =B19*1.04 -> 67392 | D19: =C19*1.04 -> 70087.68 | E19: =D19*1.04 -> 72891.187 | F19: =E19*1.04 -> 75806.835 | G19: =F19*1.04 -> 78839.108 | H19: =G19*1.04 -> 81992.672 | I19: =H19*1.04 -> 85272.379 | J19: =I19*1.04 -> 88683.274 | ... M19: =L19*1.04 -> 99756.623
A20: Kapacitetsomkostninger i alt | B20: =SUM(B15:B19) -> 818584.16 | C20: =B20*1.04 -> 851327.53 | D20: =C20*1.04 -> 885380.63 | E20: =D20*1.04 -> 920795.85 | F20: =E20*1.04 -> 957627.69 | G20: =F20*1.04 -> 995932.79 | H20: =G20*1.04 -> 1035770.1 | I20: =H20*1.04 -> 1077200.9 | J20: =I20*1.04 -> 1120288.9 | ... M20: =L20*1.04 -> 1260172.7
A21: Indtjeningsbidrag | B21: =B14-B20 -> 61124902 | C21: =C14-C20 -> 63569898 | D21: =D14-D20 -> 66112693 | E21: =E14-E20 -> 68757201 | F21: =F14-F20 -> 71507489 | G21: =G14-G20 -> 74367789 | H21: =H14-H20 -> 77342500 | I21: =I14-I20 -> 80436200 | ... M21: =M14-M20 -> 94098978
A22: Afskrivninger | B22: ='Budget lister'!E83 -> 348121.83 | C22: ='14 Driftbudget'!B22 -> 348121.83 | D22: =C22 -> 348121.83 | E22: =D22 -> 348121.83 | F22: =E22 -> 348121.83 | G22: =F22 -> 348121.83 | H22: =G22 -> 348121.83 | I22: =H22 -> 348121.83 | J22: =I22 -> 348121.83 | K22: =J22 -> 348121.83 | ... M22: =L22 -> 348121.83
A23: Resultat efter afskrivninger | B23: =B21-B22 -> 60776780 | C23: =C21-C22 -> 63221776 | D23: =D21-D22 -> 65764572 | E23: =E21-E22 -> 68409079 | F23: =F21-F22 -> 71159367 | G23: =G21-G22 -> 74019667 | H23: =H21-H22 -> 76994379 | I23: =I21-I22 -> 80088079 | ... M23: =M21-M22 -> 93750856
A24: Skat (22% af overskud ) | B24: =B23*0.22 -> 13370892 | C24: =C23*0.22 -> 13908791 | D24: =D23*0.22 -> 14468206 | E24: =E23*0.22 -> 15049997 | F24: =F23*0.22 -> 15655061 | G24: =G23*0.22 -> 16284327 | H24: =H23*0.22 -> 16938763 | I24: =I23*0.22 -> 17619377 | ... M24: =M23*0.22 -> 20625188
A25: Resultat efter skat | B25: =B23-B24 -> 47405888 | C25: =C23-C24 -> 49312985 | D25: =D23-D24 -> 51296366 | E25: =E23-E24 -> 53359082 | F25: =F23-F24 -> 55504307 | G25: =G23-G24 -> 57735340 | H25: =H23-H24 -> 60055615 | I25: =I23-I24 -> 62468701 | ... M25: =M23-M24 -> 73125667

Sheet 15 Investreringsrentabilitet
B1: Forudsætninger
B2: Anskaffelsessum | C2: ='13 Etableringsbudget'!D49 -> 9285941.3 | D2: kr.
B3: Tid, n | C3: 10 | D3: år
B4: Omsætning | C4: forskellig i hvert år | D4: kr./år
B5: Totale omkostninger (faste og variable) | C5: forskellig i hvert år | D5: kr./år
B6: Kalkulationsrentefod, i | C6: ='Budget lister'!P20 -> 0.1
A8: Kalkulation
A9: År | B9: Nettobetalinger, I-U | C9: Udbetalinger, U | D9: Indbetalinger, I | E9: Diskontering | F9: Nutidsværd med diskonterings rate, I0 - U0 | G9: NV = Nettodbetalinger / (1 + rente)^period | H9: Med kaluklationen | I9: Med NPV funktionen (per år)
A10: 0 | B10: =D10-C10 -> -9285941.3 | C10: =C2 -> 9285941.3 | D10: 0 | E10: =(1+C6)^(-A10) -> 1 | F10: =B10*E10 -> -9285941.3 | G10: =B10/(1+0.1)^A10 -> -9285941.3 | H10: =B10/(1+$C$6)^A10 -> -9285941.3
A11: 1 | B11: =D11-C11 -> 47405888 | C11: 0 | D11: ='14 Driftbudget'!B25 -> 47405888 | E11: =1/(1+$C$6)^A11 -> 0.90909091 | F11: =B11*E11 -> 43096262 | G11: =B11/(1+0.1)^A11 -> 43096262 | H11: =B11/(1+$C$6)^A11 -> 43096262
A12: 2 | B12: =D12-C12 -> 49312985 | C12: 0 | D12: ='14 Driftbudget'!C25 -> 49312985 | E12: =1/(1+$C$6)^A12 -> 0.82644628 | F12: =B12*E12 -> 40754533 | G12: =B12/(1+0.1)^A12 -> 40754533 | H12: =B12/(1+$C$6)^A12 -> 40754533
A13: 3 | B13: =D13-C13 -> 51296366 | C13: 0 | D13: ='14 Driftbudget'!D25 -> 51296366 | E13: =1/(1+$C$6)^A13 -> 0.7513148 | F13: =B13*E13 -> 38539719 | G13: =B13/(1+0.1)^A13 -> 38539719 | H13: =B13/(1+$C$6)^A13 -> 38539719
A14: 4 | B14: =D14-C14 -> 53359082 | C14: 0 | D14: ='14 Driftbudget'!E25 -> 53359082 | E14: =1/(1+$C$6)^A14 -> 0.68301346 | F14: =B14*E14 -> 36444971 | G14: =B14/(1+0.1)^A14 -> 36444971 | H14: =B14/(1+$C$6)^A14 -> 36444971
A15: 5 | B15: =D15-C15 -> 55504307 | C15: 0 | D15: ='14 Driftbudget'!F25 -> 55504307 | E15: =1/(1+$C$6)^A15 -> 0.62092132 | F15: =B15*E15 -> 34463807 | G15: =B15/(1+0.1)^A15 -> 34463807 | H15: =B15/(1+$C$6)^A15 -> 34463807
A16: 6 | B16: =D16-C16 -> 57735340 | C16: 0 | D16: ='14 Driftbudget'!G25 -> 57735340 | E16: =1/(1+$C$6)^A16 -> 0.56447393 | F16: =B16*E16 -> 32590094 | G16: =B16/(1+0.1)^A16 -> 32590094 | H16: =B16/(1+$C$6)^A16 -> 32590094
A17: 7 | B17: =D17-C17 -> 60055615 | C17: 0 | D17: ='14 Driftbudget'!H25 -> 60055615 | E17: =1/(1+$C$6)^A17 -> 0.51315812 | F17: =B17*E17 -> 30818027 | G17: =B17/(1+0.1)^A17 -> 30818027 | H17: =B17/(1+$C$6)^A17 -> 30818027
A18: 8 | B18: =D18-C18 -> 62468701 | C18: 0 | D18: ='14 Driftbudget'!I25 -> 62468701 | E18: =1/(1+$C$6)^A18 -> 0.46650738 | F18: =B18*E18 -> 29142110 | G18: =B18/(1+0.1)^A18 -> 29142110 | H18: =B18/(1+$C$6)^A18 -> 29142110
A19: 9 | B19: =D19-C19 -> 64978311 | C19: 0 | D19: ='14 Driftbudget'!J25 -> 64978311 | E19: =1/(1+$C$6)^A19 -> 0.42409762 | F19: =B19*E19 -> 27557147 | G19: =B19/(1+0.1)^A19 -> 27557147 | H19: =B19/(1+$C$6)^A19 -> 27557147
A20: 10 | B20: =D20-C20 -> 67588305 | C20: 0 | D20: ='14 Driftbudget'!K25 -> 67588305 | E20: =1/(1+$C$6)^A20 -> 0.38554329 | F20: =B20*E20 -> 26058217 | G20: =B20/(1+0.1)^A20 -> 26058217 | H20: =B20/(1+$C$6)^A20 -> 26058217
F21: =SUM(F10:F20) -> 3.3017895e+08 | H21: =SUM(H10:H20) -> 3.3017895e+08
B22: Nettonutidsværdi (NPV) | C22: =F21 -> 3.3017895e+08
